{"MSE": 159.92895606160164, "SSIM": 0.40596645016921684, "example_num": 1024, "batch_step": 32, "epoch": 0, "timestamp": 1773552903, "checkpoint_dir_name": null, "done": false, "training_iteration": 1, "trial_id": "76e49193", "date": "2026-03-15_00-35-03", "time_this_iter_s": 5.304049968719482, "time_total_s": 5.304049968719482, "pid": 11544, "hostname": "DESKTOP-6E08LRQ", "node_ip": "127.0.0.1", "config": {"SI_gen_mult": 1.1608267138663855, "SI_gen_fill": 0, "SI_gen_neck": "wide", "SI_gen_z_dim": 1368, "SI_pad_mode": "zeros", "SI_dropout": false, "SI_exp_kernel": 4, "SI_gen_hidden_dim": 20, "SI_skip_mode": "conv", "SI_stats_criterion": -1, "SI_moment_1_fraction": -1, "SI_alpha_min": -1, "SI_half_life_examples": -1, "SI_disc_hidden_dim": 1, "SI_disc_patchGAN": 1, "SI_disc_lr": 1, "SI_disc_b1": 1, "SI_disc_b2": 1, "SI_disc_adv_criterion": 1, "SI_normalize": false, "SI_fixedScale": 1, "SI_learnedScale_init": 16.17836037187811, "SI_output_scale_lr_mult": 2.4740060905127015, "SI_layer_norm": "instance", "SI_gen_final_activ": null, "batch_base2_exponent": 5, "gen_lr": 0.002252812073496261, "gen_b1": 0.3780182972970298, "gen_b2": 0.32535018061489646, "sup_base_criterion": "MSELoss", "IS_disc_hidden_dim": 1, "IS_disc_patchGAN": 1, "IS_disc_lr": 1, "IS_disc_b1": 1, "IS_disc_b2": 1, "IS_disc_adv_criterion": 1, "network_type": "ACT", "train_SI": true, "gen_image_size": 180, "gen_sino_size": 288, "gen_image_channels": 1, "gen_sino_channels": 3}, "time_since_restore": 5.304049968719482, "iterations_since_restore": 1}
{"MSE": 121.03126817941666, "SSIM": 0.6225685043027624, "example_num": 2048, "batch_step": 64, "epoch": 0, "timestamp": 1773552907, "checkpoint_dir_name": null, "done": false, "training_iteration": 2, "trial_id": "76e49193", "date": "2026-03-15_00-35-07", "time_this_iter_s": 4.188210725784302, "time_total_s": 9.492260694503784, "pid": 11544, "hostname": "DESKTOP-6E08LRQ", "node_ip": "127.0.0.1", "config": {"SI_gen_mult": 1.1608267138663855, "SI_gen_fill": 0, "SI_gen_neck": "wide", "SI_gen_z_dim": 1368, "SI_pad_mode": "zeros", "SI_dropout": false, "SI_exp_kernel": 4, "SI_gen_hidden_dim": 20, "SI_skip_mode": "conv", "SI_stats_criterion": -1, "SI_moment_1_fraction": -1, "SI_alpha_min": -1, "SI_half_life_examples": -1, "SI_disc_hidden_dim": 1, "SI_disc_patchGAN": 1, "SI_disc_lr": 1, "SI_disc_b1": 1, "SI_disc_b2": 1, "SI_disc_adv_criterion": 1, "SI_normalize": false, "SI_fixedScale": 1, "SI_learnedScale_init": 16.17836037187811, "SI_output_scale_lr_mult": 2.4740060905127015, "SI_layer_norm": "instance", "SI_gen_final_activ": null, "batch_base2_exponent": 5, "gen_lr": 0.002252812073496261, "gen_b1": 0.3780182972970298, "gen_b2": 0.32535018061489646, "sup_base_criterion": "MSELoss", "IS_disc_hidden_dim": 1, "IS_disc_patchGAN": 1, "IS_disc_lr": 1, "IS_disc_b1": 1, "IS_disc_b2": 1, "IS_disc_adv_criterion": 1, "network_type": "ACT", "train_SI": true, "gen_image_size": 180, "gen_sino_size": 288, "gen_image_channels": 1, "gen_sino_channels": 3}, "time_since_restore": 9.492260694503784, "iterations_since_restore": 2}
{"MSE": 100.65644636750221, "SSIM": 0.5908315913984552, "example_num": 3072, "batch_step": 96, "epoch": 0, "timestamp": 1773552911, "checkpoint_dir_name": null, "done": false, "training_iteration": 3, "trial_id": "76e49193", "date": "2026-03-15_00-35-11", "time_this_iter_s": 4.097421646118164, "time_total_s": 13.589682340621948, "pid": 11544, "hostname": "DESKTOP-6E08LRQ", "node_ip": "127.0.0.1", "config": {"SI_gen_mult": 1.1608267138663855, "SI_gen_fill": 0, "SI_gen_neck": "wide", "SI_gen_z_dim": 1368, "SI_pad_mode": "zeros", "SI_dropout": false, "SI_exp_kernel": 4, "SI_gen_hidden_dim": 20, "SI_skip_mode": "conv", "SI_stats_criterion": -1, "SI_moment_1_fraction": -1, "SI_alpha_min": -1, "SI_half_life_examples": -1, "SI_disc_hidden_dim": 1, "SI_disc_patchGAN": 1, "SI_disc_lr": 1, "SI_disc_b1": 1, "SI_disc_b2": 1, "SI_disc_adv_criterion": 1, "SI_normalize": false, "SI_fixedScale": 1, "SI_learnedScale_init": 16.17836037187811, "SI_output_scale_lr_mult": 2.4740060905127015, "SI_layer_norm": "instance", "SI_gen_final_activ": null, "batch_base2_exponent": 5, "gen_lr": 0.002252812073496261, "gen_b1": 0.3780182972970298, "gen_b2": 0.32535018061489646, "sup_base_criterion": "MSELoss", "IS_disc_hidden_dim": 1, "IS_disc_patchGAN": 1, "IS_disc_lr": 1, "IS_disc_b1": 1, "IS_disc_b2": 1, "IS_disc_adv_criterion": 1, "network_type": "ACT", "train_SI": true, "gen_image_size": 180, "gen_sino_size": 288, "gen_image_channels": 1, "gen_sino_channels": 3}, "time_since_restore": 13.589682340621948, "iterations_since_restore": 3}
{"MSE": 120.23292036354542, "SSIM": 0.6830434519797564, "example_num": 4096, "batch_step": 128, "epoch": 0, "timestamp": 1773552915, "checkpoint_dir_name": null, "done": false, "training_iteration": 4, "trial_id": "76e49193", "date": "2026-03-15_00-35-15", "time_this_iter_s": 4.105128288269043, "time_total_s": 17.69481062889099, "pid": 11544, "hostname": "DESKTOP-6E08LRQ", "node_ip": "127.0.0.1", "config": {"SI_gen_mult": 1.1608267138663855, "SI_gen_fill": 0, "SI_gen_neck": "wide", "SI_gen_z_dim": 1368, "SI_pad_mode": "zeros", "SI_dropout": false, "SI_exp_kernel": 4, "SI_gen_hidden_dim": 20, "SI_skip_mode": "conv", "SI_stats_criterion": -1, "SI_moment_1_fraction": -1, "SI_alpha_min": -1, "SI_half_life_examples": -1, "SI_disc_hidden_dim": 1, "SI_disc_patchGAN": 1, "SI_disc_lr": 1, "SI_disc_b1": 1, "SI_disc_b2": 1, "SI_disc_adv_criterion": 1, "SI_normalize": false, "SI_fixedScale": 1, "SI_learnedScale_init": 16.17836037187811, "SI_output_scale_lr_mult": 2.4740060905127015, "SI_layer_norm": "instance", "SI_gen_final_activ": null, "batch_base2_exponent": 5, "gen_lr": 0.002252812073496261, "gen_b1": 0.3780182972970298, "gen_b2": 0.32535018061489646, "sup_base_criterion": "MSELoss", "IS_disc_hidden_dim": 1, "IS_disc_patchGAN": 1, "IS_disc_lr": 1, "IS_disc_b1": 1, "IS_disc_b2": 1, "IS_disc_adv_criterion": 1, "network_type": "ACT", "train_SI": true, "gen_image_size": 180, "gen_sino_size": 288, "gen_image_channels": 1, "gen_sino_channels": 3}, "time_since_restore": 17.69481062889099, "iterations_since_restore": 4}
{"MSE": 88.35377483069897, "SSIM": 0.632617303985171, "example_num": 5120, "batch_step": 160, "epoch": 0, "timestamp": 1773552920, "checkpoint_dir_name": null, "done": false, "training_iteration": 5, "trial_id": "76e49193", "date": "2026-03-15_00-35-20", "time_this_iter_s": 4.392547607421875, "time_total_s": 22.087358236312866, "pid": 11544, "hostname": "DESKTOP-6E08LRQ", "node_ip": "127.0.0.1", "config": {"SI_gen_mult": 1.1608267138663855, "SI_gen_fill": 0, "SI_gen_neck": "wide", "SI_gen_z_dim": 1368, "SI_pad_mode": "zeros", "SI_dropout": false, "SI_exp_kernel": 4, "SI_gen_hidden_dim": 20, "SI_skip_mode": "conv", "SI_stats_criterion": -1, "SI_moment_1_fraction": -1, "SI_alpha_min": -1, "SI_half_life_examples": -1, "SI_disc_hidden_dim": 1, "SI_disc_patchGAN": 1, "SI_disc_lr": 1, "SI_disc_b1": 1, "SI_disc_b2": 1, "SI_disc_adv_criterion": 1, "SI_normalize": false, "SI_fixedScale": 1, "SI_learnedScale_init": 16.17836037187811, "SI_output_scale_lr_mult": 2.4740060905127015, "SI_layer_norm": "instance", "SI_gen_final_activ": null, "batch_base2_exponent": 5, "gen_lr": 0.002252812073496261, "gen_b1": 0.3780182972970298, "gen_b2": 0.32535018061489646, "sup_base_criterion": "MSELoss", "IS_disc_hidden_dim": 1, "IS_disc_patchGAN": 1, "IS_disc_lr": 1, "IS_disc_b1": 1, "IS_disc_b2": 1, "IS_disc_adv_criterion": 1, "network_type": "ACT", "train_SI": true, "gen_image_size": 180, "gen_sino_size": 288, "gen_image_channels": 1, "gen_sino_channels": 3}, "time_since_restore": 22.087358236312866, "iterations_since_restore": 5}
{"MSE": 77.46421302855015, "SSIM": 0.725540055311285, "example_num": 6144, "batch_step": 192, "epoch": 0, "timestamp": 1773552925, "checkpoint_dir_name": null, "done": false, "training_iteration": 6, "trial_id": "76e49193", "date": "2026-03-15_00-35-25", "time_this_iter_s": 5.301276922225952, "time_total_s": 27.38863515853882, "pid": 11544, "hostname": "DESKTOP-6E08LRQ", "node_ip": "127.0.0.1", "config": {"SI_gen_mult": 1.1608267138663855, "SI_gen_fill": 0, "SI_gen_neck": "wide", "SI_gen_z_dim": 1368, "SI_pad_mode": "zeros", "SI_dropout": false, "SI_exp_kernel": 4, "SI_gen_hidden_dim": 20, "SI_skip_mode": "conv", "SI_stats_criterion": -1, "SI_moment_1_fraction": -1, "SI_alpha_min": -1, "SI_half_life_examples": -1, "SI_disc_hidden_dim": 1, "SI_disc_patchGAN": 1, "SI_disc_lr": 1, "SI_disc_b1": 1, "SI_disc_b2": 1, "SI_disc_adv_criterion": 1, "SI_normalize": false, "SI_fixedScale": 1, "SI_learnedScale_init": 16.17836037187811, "SI_output_scale_lr_mult": 2.4740060905127015, "SI_layer_norm": "instance", "SI_gen_final_activ": null, "batch_base2_exponent": 5, "gen_lr": 0.002252812073496261, "gen_b1": 0.3780182972970298, "gen_b2": 0.32535018061489646, "sup_base_criterion": "MSELoss", "IS_disc_hidden_dim": 1, "IS_disc_patchGAN": 1, "IS_disc_lr": 1, "IS_disc_b1": 1, "IS_disc_b2": 1, "IS_disc_adv_criterion": 1, "network_type": "ACT", "train_SI": true, "gen_image_size": 180, "gen_sino_size": 288, "gen_image_channels": 1, "gen_sino_channels": 3}, "time_since_restore": 27.38863515853882, "iterations_since_restore": 6}
{"MSE": 105.08294497430325, "SSIM": 0.6601481588440947, "example_num": 7168, "batch_step": 224, "epoch": 0, "timestamp": 1773552929, "checkpoint_dir_name": null, "done": false, "training_iteration": 7, "trial_id": "76e49193", "date": "2026-03-15_00-35-29", "time_this_iter_s": 4.14247989654541, "time_total_s": 31.53111505508423, "pid": 11544, "hostname": "DESKTOP-6E08LRQ", "node_ip": "127.0.0.1", "config": {"SI_gen_mult": 1.1608267138663855, "SI_gen_fill": 0, "SI_gen_neck": "wide", "SI_gen_z_dim": 1368, "SI_pad_mode": "zeros", "SI_dropout": false, "SI_exp_kernel": 4, "SI_gen_hidden_dim": 20, "SI_skip_mode": "conv", "SI_stats_criterion": -1, "SI_moment_1_fraction": -1, "SI_alpha_min": -1, "SI_half_life_examples": -1, "SI_disc_hidden_dim": 1, "SI_disc_patchGAN": 1, "SI_disc_lr": 1, "SI_disc_b1": 1, "SI_disc_b2": 1, "SI_disc_adv_criterion": 1, "SI_normalize": false, "SI_fixedScale": 1, "SI_learnedScale_init": 16.17836037187811, "SI_output_scale_lr_mult": 2.4740060905127015, "SI_layer_norm": "instance", "SI_gen_final_activ": null, "batch_base2_exponent": 5, "gen_lr": 0.002252812073496261, "gen_b1": 0.3780182972970298, "gen_b2": 0.32535018061489646, "sup_base_criterion": "MSELoss", "IS_disc_hidden_dim": 1, "IS_disc_patchGAN": 1, "IS_disc_lr": 1, "IS_disc_b1": 1, "IS_disc_b2": 1, "IS_disc_adv_criterion": 1, "network_type": "ACT", "train_SI": true, "gen_image_size": 180, "gen_sino_size": 288, "gen_image_channels": 1, "gen_sino_channels": 3}, "time_since_restore": 31.53111505508423, "iterations_since_restore": 7}
{"MSE": 67.67233908176422, "SSIM": 0.7653430459322408, "example_num": 8192, "batch_step": 256, "epoch": 0, "timestamp": 1773552933, "checkpoint_dir_name": null, "done": false, "training_iteration": 8, "trial_id": "76e49193", "date": "2026-03-15_00-35-33", "time_this_iter_s": 4.246710300445557, "time_total_s": 35.777825355529785, "pid": 11544, "hostname": "DESKTOP-6E08LRQ", "node_ip": "127.0.0.1", "config": {"SI_gen_mult": 1.1608267138663855, "SI_gen_fill": 0, "SI_gen_neck": "wide", "SI_gen_z_dim": 1368, "SI_pad_mode": "zeros", "SI_dropout": false, "SI_exp_kernel": 4, "SI_gen_hidden_dim": 20, "SI_skip_mode": "conv", "SI_stats_criterion": -1, "SI_moment_1_fraction": -1, "SI_alpha_min": -1, "SI_half_life_examples": -1, "SI_disc_hidden_dim": 1, "SI_disc_patchGAN": 1, "SI_disc_lr": 1, "SI_disc_b1": 1, "SI_disc_b2": 1, "SI_disc_adv_criterion": 1, "SI_normalize": false, "SI_fixedScale": 1, "SI_learnedScale_init": 16.17836037187811, "SI_output_scale_lr_mult": 2.4740060905127015, "SI_layer_norm": "instance", "SI_gen_final_activ": null, "batch_base2_exponent": 5, "gen_lr": 0.002252812073496261, "gen_b1": 0.3780182972970298, "gen_b2": 0.32535018061489646, "sup_base_criterion": "MSELoss", "IS_disc_hidden_dim": 1, "IS_disc_patchGAN": 1, "IS_disc_lr": 1, "IS_disc_b1": 1, "IS_disc_b2": 1, "IS_disc_adv_criterion": 1, "network_type": "ACT", "train_SI": true, "gen_image_size": 180, "gen_sino_size": 288, "gen_image_channels": 1, "gen_sino_channels": 3}, "time_since_restore": 35.777825355529785, "iterations_since_restore": 8}
{"MSE": 68.91976869106293, "SSIM": 0.6984303256613202, "example_num": 9216, "batch_step": 288, "epoch": 0, "timestamp": 1773552937, "checkpoint_dir_name": null, "done": false, "training_iteration": 9, "trial_id": "76e49193", "date": "2026-03-15_00-35-37", "time_this_iter_s": 4.015643835067749, "time_total_s": 39.793469190597534, "pid": 11544, "hostname": "DESKTOP-6E08LRQ", "node_ip": "127.0.0.1", "config": {"SI_gen_mult": 1.1608267138663855, "SI_gen_fill": 0, "SI_gen_neck": "wide", "SI_gen_z_dim": 1368, "SI_pad_mode": "zeros", "SI_dropout": false, "SI_exp_kernel": 4, "SI_gen_hidden_dim": 20, "SI_skip_mode": "conv", "SI_stats_criterion": -1, "SI_moment_1_fraction": -1, "SI_alpha_min": -1, "SI_half_life_examples": -1, "SI_disc_hidden_dim": 1, "SI_disc_patchGAN": 1, "SI_disc_lr": 1, "SI_disc_b1": 1, "SI_disc_b2": 1, "SI_disc_adv_criterion": 1, "SI_normalize": false, "SI_fixedScale": 1, "SI_learnedScale_init": 16.17836037187811, "SI_output_scale_lr_mult": 2.4740060905127015, "SI_layer_norm": "instance", "SI_gen_final_activ": null, "batch_base2_exponent": 5, "gen_lr": 0.002252812073496261, "gen_b1": 0.3780182972970298, "gen_b2": 0.32535018061489646, "sup_base_criterion": "MSELoss", "IS_disc_hidden_dim": 1, "IS_disc_patchGAN": 1, "IS_disc_lr": 1, "IS_disc_b1": 1, "IS_disc_b2": 1, "IS_disc_adv_criterion": 1, "network_type": "ACT", "train_SI": true, "gen_image_size": 180, "gen_sino_size": 288, "gen_image_channels": 1, "gen_sino_channels": 3}, "time_since_restore": 39.793469190597534, "iterations_since_restore": 9}
{"MSE": 55.131758630275726, "SSIM": 0.7562458818210871, "example_num": 10240, "batch_step": 320, "epoch": 0, "timestamp": 1773552941, "checkpoint_dir_name": null, "done": false, "training_iteration": 10, "trial_id": "76e49193", "date": "2026-03-15_00-35-41", "time_this_iter_s": 4.028031587600708, "time_total_s": 43.82150077819824, "pid": 11544, "hostname": "DESKTOP-6E08LRQ", "node_ip": "127.0.0.1", "config": {"SI_gen_mult": 1.1608267138663855, "SI_gen_fill": 0, "SI_gen_neck": "wide", "SI_gen_z_dim": 1368, "SI_pad_mode": "zeros", "SI_dropout": false, "SI_exp_kernel": 4, "SI_gen_hidden_dim": 20, "SI_skip_mode": "conv", "SI_stats_criterion": -1, "SI_moment_1_fraction": -1, "SI_alpha_min": -1, "SI_half_life_examples": -1, "SI_disc_hidden_dim": 1, "SI_disc_patchGAN": 1, "SI_disc_lr": 1, "SI_disc_b1": 1, "SI_disc_b2": 1, "SI_disc_adv_criterion": 1, "SI_normalize": false, "SI_fixedScale": 1, "SI_learnedScale_init": 16.17836037187811, "SI_output_scale_lr_mult": 2.4740060905127015, "SI_layer_norm": "instance", "SI_gen_final_activ": null, "batch_base2_exponent": 5, "gen_lr": 0.002252812073496261, "gen_b1": 0.3780182972970298, "gen_b2": 0.32535018061489646, "sup_base_criterion": "MSELoss", "IS_disc_hidden_dim": 1, "IS_disc_patchGAN": 1, "IS_disc_lr": 1, "IS_disc_b1": 1, "IS_disc_b2": 1, "IS_disc_adv_criterion": 1, "network_type": "ACT", "train_SI": true, "gen_image_size": 180, "gen_sino_size": 288, "gen_image_channels": 1, "gen_sino_channels": 3}, "time_since_restore": 43.82150077819824, "iterations_since_restore": 10}
{"MSE": 62.12077817320824, "SSIM": 0.7806663317605853, "example_num": 11264, "batch_step": 352, "epoch": 0, "timestamp": 1773552945, "checkpoint_dir_name": null, "done": false, "training_iteration": 11, "trial_id": "76e49193", "date": "2026-03-15_00-35-45", "time_this_iter_s": 4.176850318908691, "time_total_s": 47.998351097106934, "pid": 11544, "hostname": "DESKTOP-6E08LRQ", "node_ip": "127.0.0.1", "config": {"SI_gen_mult": 1.1608267138663855, "SI_gen_fill": 0, "SI_gen_neck": "wide", "SI_gen_z_dim": 1368, "SI_pad_mode": "zeros", "SI_dropout": false, "SI_exp_kernel": 4, "SI_gen_hidden_dim": 20, "SI_skip_mode": "conv", "SI_stats_criterion": -1, "SI_moment_1_fraction": -1, "SI_alpha_min": -1, "SI_half_life_examples": -1, "SI_disc_hidden_dim": 1, "SI_disc_patchGAN": 1, "SI_disc_lr": 1, "SI_disc_b1": 1, "SI_disc_b2": 1, "SI_disc_adv_criterion": 1, "SI_normalize": false, "SI_fixedScale": 1, "SI_learnedScale_init": 16.17836037187811, "SI_output_scale_lr_mult": 2.4740060905127015, "SI_layer_norm": "instance", "SI_gen_final_activ": null, "batch_base2_exponent": 5, "gen_lr": 0.002252812073496261, "gen_b1": 0.3780182972970298, "gen_b2": 0.32535018061489646, "sup_base_criterion": "MSELoss", "IS_disc_hidden_dim": 1, "IS_disc_patchGAN": 1, "IS_disc_lr": 1, "IS_disc_b1": 1, "IS_disc_b2": 1, "IS_disc_adv_criterion": 1, "network_type": "ACT", "train_SI": true, "gen_image_size": 180, "gen_sino_size": 288, "gen_image_channels": 1, "gen_sino_channels": 3}, "time_since_restore": 47.998351097106934, "iterations_since_restore": 11}
{"MSE": 87.31133548915386, "SSIM": 0.7782912410330027, "example_num": 12288, "batch_step": 384, "epoch": 0, "timestamp": 1773552950, "checkpoint_dir_name": null, "done": false, "training_iteration": 12, "trial_id": "76e49193", "date": "2026-03-15_00-35-50", "time_this_iter_s": 4.208086252212524, "time_total_s": 52.20643734931946, "pid": 11544, "hostname": "DESKTOP-6E08LRQ", "node_ip": "127.0.0.1", "config": {"SI_gen_mult": 1.1608267138663855, "SI_gen_fill": 0, "SI_gen_neck": "wide", "SI_gen_z_dim": 1368, "SI_pad_mode": "zeros", "SI_dropout": false, "SI_exp_kernel": 4, "SI_gen_hidden_dim": 20, "SI_skip_mode": "conv", "SI_stats_criterion": -1, "SI_moment_1_fraction": -1, "SI_alpha_min": -1, "SI_half_life_examples": -1, "SI_disc_hidden_dim": 1, "SI_disc_patchGAN": 1, "SI_disc_lr": 1, "SI_disc_b1": 1, "SI_disc_b2": 1, "SI_disc_adv_criterion": 1, "SI_normalize": false, "SI_fixedScale": 1, "SI_learnedScale_init": 16.17836037187811, "SI_output_scale_lr_mult": 2.4740060905127015, "SI_layer_norm": "instance", "SI_gen_final_activ": null, "batch_base2_exponent": 5, "gen_lr": 0.002252812073496261, "gen_b1": 0.3780182972970298, "gen_b2": 0.32535018061489646, "sup_base_criterion": "MSELoss", "IS_disc_hidden_dim": 1, "IS_disc_patchGAN": 1, "IS_disc_lr": 1, "IS_disc_b1": 1, "IS_disc_b2": 1, "IS_disc_adv_criterion": 1, "network_type": "ACT", "train_SI": true, "gen_image_size": 180, "gen_sino_size": 288, "gen_image_channels": 1, "gen_sino_channels": 3}, "time_since_restore": 52.20643734931946, "iterations_since_restore": 12}
{"MSE": 73.68486420810223, "SSIM": 0.7915799936745316, "example_num": 13312, "batch_step": 416, "epoch": 0, "timestamp": 1773552955, "checkpoint_dir_name": null, "done": false, "training_iteration": 13, "trial_id": "76e49193", "date": "2026-03-15_00-35-55", "time_this_iter_s": 5.072143077850342, "time_total_s": 57.2785804271698, "pid": 11544, "hostname": "DESKTOP-6E08LRQ", "node_ip": "127.0.0.1", "config": {"SI_gen_mult": 1.1608267138663855, "SI_gen_fill": 0, "SI_gen_neck": "wide", "SI_gen_z_dim": 1368, "SI_pad_mode": "zeros", "SI_dropout": false, "SI_exp_kernel": 4, "SI_gen_hidden_dim": 20, "SI_skip_mode": "conv", "SI_stats_criterion": -1, "SI_moment_1_fraction": -1, "SI_alpha_min": -1, "SI_half_life_examples": -1, "SI_disc_hidden_dim": 1, "SI_disc_patchGAN": 1, "SI_disc_lr": 1, "SI_disc_b1": 1, "SI_disc_b2": 1, "SI_disc_adv_criterion": 1, "SI_normalize": false, "SI_fixedScale": 1, "SI_learnedScale_init": 16.17836037187811, "SI_output_scale_lr_mult": 2.4740060905127015, "SI_layer_norm": "instance", "SI_gen_final_activ": null, "batch_base2_exponent": 5, "gen_lr": 0.002252812073496261, "gen_b1": 0.3780182972970298, "gen_b2": 0.32535018061489646, "sup_base_criterion": "MSELoss", "IS_disc_hidden_dim": 1, "IS_disc_patchGAN": 1, "IS_disc_lr": 1, "IS_disc_b1": 1, "IS_disc_b2": 1, "IS_disc_adv_criterion": 1, "network_type": "ACT", "train_SI": true, "gen_image_size": 180, "gen_sino_size": 288, "gen_image_channels": 1, "gen_sino_channels": 3}, "time_since_restore": 57.2785804271698, "iterations_since_restore": 13}
{"MSE": 77.61198578774929, "SSIM": 0.6168104411335662, "example_num": 14336, "batch_step": 448, "epoch": 0, "timestamp": 1773552959, "checkpoint_dir_name": null, "done": false, "training_iteration": 14, "trial_id": "76e49193", "date": "2026-03-15_00-35-59", "time_this_iter_s": 4.028096675872803, "time_total_s": 61.3066771030426, "pid": 11544, "hostname": "DESKTOP-6E08LRQ", "node_ip": "127.0.0.1", "config": {"SI_gen_mult": 1.1608267138663855, "SI_gen_fill": 0, "SI_gen_neck": "wide", "SI_gen_z_dim": 1368, "SI_pad_mode": "zeros", "SI_dropout": false, "SI_exp_kernel": 4, "SI_gen_hidden_dim": 20, "SI_skip_mode": "conv", "SI_stats_criterion": -1, "SI_moment_1_fraction": -1, "SI_alpha_min": -1, "SI_half_life_examples": -1, "SI_disc_hidden_dim": 1, "SI_disc_patchGAN": 1, "SI_disc_lr": 1, "SI_disc_b1": 1, "SI_disc_b2": 1, "SI_disc_adv_criterion": 1, "SI_normalize": false, "SI_fixedScale": 1, "SI_learnedScale_init": 16.17836037187811, "SI_output_scale_lr_mult": 2.4740060905127015, "SI_layer_norm": "instance", "SI_gen_final_activ": null, "batch_base2_exponent": 5, "gen_lr": 0.002252812073496261, "gen_b1": 0.3780182972970298, "gen_b2": 0.32535018061489646, "sup_base_criterion": "MSELoss", "IS_disc_hidden_dim": 1, "IS_disc_patchGAN": 1, "IS_disc_lr": 1, "IS_disc_b1": 1, "IS_disc_b2": 1, "IS_disc_adv_criterion": 1, "network_type": "ACT", "train_SI": true, "gen_image_size": 180, "gen_sino_size": 288, "gen_image_channels": 1, "gen_sino_channels": 3}, "time_since_restore": 61.3066771030426, "iterations_since_restore": 14}
{"MSE": 70.34215718507767, "SSIM": 0.7667170162312686, "example_num": 15360, "batch_step": 480, "epoch": 0, "timestamp": 1773552964, "checkpoint_dir_name": null, "done": false, "training_iteration": 15, "trial_id": "76e49193", "date": "2026-03-15_00-36-04", "time_this_iter_s": 4.790370941162109, "time_total_s": 66.09704804420471, "pid": 11544, "hostname": "DESKTOP-6E08LRQ", "node_ip": "127.0.0.1", "config": {"SI_gen_mult": 1.1608267138663855, "SI_gen_fill": 0, "SI_gen_neck": "wide", "SI_gen_z_dim": 1368, "SI_pad_mode": "zeros", "SI_dropout": false, "SI_exp_kernel": 4, "SI_gen_hidden_dim": 20, "SI_skip_mode": "conv", "SI_stats_criterion": -1, "SI_moment_1_fraction": -1, "SI_alpha_min": -1, "SI_half_life_examples": -1, "SI_disc_hidden_dim": 1, "SI_disc_patchGAN": 1, "SI_disc_lr": 1, "SI_disc_b1": 1, "SI_disc_b2": 1, "SI_disc_adv_criterion": 1, "SI_normalize": false, "SI_fixedScale": 1, "SI_learnedScale_init": 16.17836037187811, "SI_output_scale_lr_mult": 2.4740060905127015, "SI_layer_norm": "instance", "SI_gen_final_activ": null, "batch_base2_exponent": 5, "gen_lr": 0.002252812073496261, "gen_b1": 0.3780182972970298, "gen_b2": 0.32535018061489646, "sup_base_criterion": "MSELoss", "IS_disc_hidden_dim": 1, "IS_disc_patchGAN": 1, "IS_disc_lr": 1, "IS_disc_b1": 1, "IS_disc_b2": 1, "IS_disc_adv_criterion": 1, "network_type": "ACT", "train_SI": true, "gen_image_size": 180, "gen_sino_size": 288, "gen_image_channels": 1, "gen_sino_channels": 3}, "time_since_restore": 66.09704804420471, "iterations_since_restore": 15}
{"MSE": 78.11800207197666, "SSIM": 0.8124006206635386, "example_num": 16384, "batch_step": 512, "epoch": 0, "timestamp": 1773552968, "checkpoint_dir_name": null, "done": false, "training_iteration": 16, "trial_id": "76e49193", "date": "2026-03-15_00-36-08", "time_this_iter_s": 4.237468719482422, "time_total_s": 70.33451676368713, "pid": 11544, "hostname": "DESKTOP-6E08LRQ", "node_ip": "127.0.0.1", "config": {"SI_gen_mult": 1.1608267138663855, "SI_gen_fill": 0, "SI_gen_neck": "wide", "SI_gen_z_dim": 1368, "SI_pad_mode": "zeros", "SI_dropout": false, "SI_exp_kernel": 4, "SI_gen_hidden_dim": 20, "SI_skip_mode": "conv", "SI_stats_criterion": -1, "SI_moment_1_fraction": -1, "SI_alpha_min": -1, "SI_half_life_examples": -1, "SI_disc_hidden_dim": 1, "SI_disc_patchGAN": 1, "SI_disc_lr": 1, "SI_disc_b1": 1, "SI_disc_b2": 1, "SI_disc_adv_criterion": 1, "SI_normalize": false, "SI_fixedScale": 1, "SI_learnedScale_init": 16.17836037187811, "SI_output_scale_lr_mult": 2.4740060905127015, "SI_layer_norm": "instance", "SI_gen_final_activ": null, "batch_base2_exponent": 5, "gen_lr": 0.002252812073496261, "gen_b1": 0.3780182972970298, "gen_b2": 0.32535018061489646, "sup_base_criterion": "MSELoss", "IS_disc_hidden_dim": 1, "IS_disc_patchGAN": 1, "IS_disc_lr": 1, "IS_disc_b1": 1, "IS_disc_b2": 1, "IS_disc_adv_criterion": 1, "network_type": "ACT", "train_SI": true, "gen_image_size": 180, "gen_sino_size": 288, "gen_image_channels": 1, "gen_sino_channels": 3}, "time_since_restore": 70.33451676368713, "iterations_since_restore": 16}
{"MSE": 91.72157491743565, "SSIM": 0.7566607946064323, "example_num": 17408, "batch_step": 544, "epoch": 0, "timestamp": 1773552973, "checkpoint_dir_name": null, "done": false, "training_iteration": 17, "trial_id": "76e49193", "date": "2026-03-15_00-36-13", "time_this_iter_s": 4.861506462097168, "time_total_s": 75.1960232257843, "pid": 11544, "hostname": "DESKTOP-6E08LRQ", "node_ip": "127.0.0.1", "config": {"SI_gen_mult": 1.1608267138663855, "SI_gen_fill": 0, "SI_gen_neck": "wide", "SI_gen_z_dim": 1368, "SI_pad_mode": "zeros", "SI_dropout": false, "SI_exp_kernel": 4, "SI_gen_hidden_dim": 20, "SI_skip_mode": "conv", "SI_stats_criterion": -1, "SI_moment_1_fraction": -1, "SI_alpha_min": -1, "SI_half_life_examples": -1, "SI_disc_hidden_dim": 1, "SI_disc_patchGAN": 1, "SI_disc_lr": 1, "SI_disc_b1": 1, "SI_disc_b2": 1, "SI_disc_adv_criterion": 1, "SI_normalize": false, "SI_fixedScale": 1, "SI_learnedScale_init": 16.17836037187811, "SI_output_scale_lr_mult": 2.4740060905127015, "SI_layer_norm": "instance", "SI_gen_final_activ": null, "batch_base2_exponent": 5, "gen_lr": 0.002252812073496261, "gen_b1": 0.3780182972970298, "gen_b2": 0.32535018061489646, "sup_base_criterion": "MSELoss", "IS_disc_hidden_dim": 1, "IS_disc_patchGAN": 1, "IS_disc_lr": 1, "IS_disc_b1": 1, "IS_disc_b2": 1, "IS_disc_adv_criterion": 1, "network_type": "ACT", "train_SI": true, "gen_image_size": 180, "gen_sino_size": 288, "gen_image_channels": 1, "gen_sino_channels": 3}, "time_since_restore": 75.1960232257843, "iterations_since_restore": 17}
{"MSE": 64.5915409475565, "SSIM": 0.7857048674486578, "example_num": 18432, "batch_step": 576, "epoch": 1, "timestamp": 1773552977, "checkpoint_dir_name": null, "done": false, "training_iteration": 18, "trial_id": "76e49193", "date": "2026-03-15_00-36-17", "time_this_iter_s": 4.2104291915893555, "time_total_s": 79.40645241737366, "pid": 11544, "hostname": "DESKTOP-6E08LRQ", "node_ip": "127.0.0.1", "config": {"SI_gen_mult": 1.1608267138663855, "SI_gen_fill": 0, "SI_gen_neck": "wide", "SI_gen_z_dim": 1368, "SI_pad_mode": "zeros", "SI_dropout": false, "SI_exp_kernel": 4, "SI_gen_hidden_dim": 20, "SI_skip_mode": "conv", "SI_stats_criterion": -1, "SI_moment_1_fraction": -1, "SI_alpha_min": -1, "SI_half_life_examples": -1, "SI_disc_hidden_dim": 1, "SI_disc_patchGAN": 1, "SI_disc_lr": 1, "SI_disc_b1": 1, "SI_disc_b2": 1, "SI_disc_adv_criterion": 1, "SI_normalize": false, "SI_fixedScale": 1, "SI_learnedScale_init": 16.17836037187811, "SI_output_scale_lr_mult": 2.4740060905127015, "SI_layer_norm": "instance", "SI_gen_final_activ": null, "batch_base2_exponent": 5, "gen_lr": 0.002252812073496261, "gen_b1": 0.3780182972970298, "gen_b2": 0.32535018061489646, "sup_base_criterion": "MSELoss", "IS_disc_hidden_dim": 1, "IS_disc_patchGAN": 1, "IS_disc_lr": 1, "IS_disc_b1": 1, "IS_disc_b2": 1, "IS_disc_adv_criterion": 1, "network_type": "ACT", "train_SI": true, "gen_image_size": 180, "gen_sino_size": 288, "gen_image_channels": 1, "gen_sino_channels": 3}, "time_since_restore": 79.40645241737366, "iterations_since_restore": 18}
{"MSE": 63.10589848458767, "SSIM": 0.7838750034570694, "example_num": 19456, "batch_step": 608, "epoch": 1, "timestamp": 1773552981, "checkpoint_dir_name": null, "done": false, "training_iteration": 19, "trial_id": "76e49193", "date": "2026-03-15_00-36-21", "time_this_iter_s": 4.034368991851807, "time_total_s": 83.44082140922546, "pid": 11544, "hostname": "DESKTOP-6E08LRQ", "node_ip": "127.0.0.1", "config": {"SI_gen_mult": 1.1608267138663855, "SI_gen_fill": 0, "SI_gen_neck": "wide", "SI_gen_z_dim": 1368, "SI_pad_mode": "zeros", "SI_dropout": false, "SI_exp_kernel": 4, "SI_gen_hidden_dim": 20, "SI_skip_mode": "conv", "SI_stats_criterion": -1, "SI_moment_1_fraction": -1, "SI_alpha_min": -1, "SI_half_life_examples": -1, "SI_disc_hidden_dim": 1, "SI_disc_patchGAN": 1, "SI_disc_lr": 1, "SI_disc_b1": 1, "SI_disc_b2": 1, "SI_disc_adv_criterion": 1, "SI_normalize": false, "SI_fixedScale": 1, "SI_learnedScale_init": 16.17836037187811, "SI_output_scale_lr_mult": 2.4740060905127015, "SI_layer_norm": "instance", "SI_gen_final_activ": null, "batch_base2_exponent": 5, "gen_lr": 0.002252812073496261, "gen_b1": 0.3780182972970298, "gen_b2": 0.32535018061489646, "sup_base_criterion": "MSELoss", "IS_disc_hidden_dim": 1, "IS_disc_patchGAN": 1, "IS_disc_lr": 1, "IS_disc_b1": 1, "IS_disc_b2": 1, "IS_disc_adv_criterion": 1, "network_type": "ACT", "train_SI": true, "gen_image_size": 180, "gen_sino_size": 288, "gen_image_channels": 1, "gen_sino_channels": 3}, "time_since_restore": 83.44082140922546, "iterations_since_restore": 19}
{"MSE": 79.66796772181988, "SSIM": 0.7979023691732436, "example_num": 20480, "batch_step": 640, "epoch": 1, "timestamp": 1773552985, "checkpoint_dir_name": null, "done": false, "training_iteration": 20, "trial_id": "76e49193", "date": "2026-03-15_00-36-25", "time_this_iter_s": 4.051975965499878, "time_total_s": 87.49279737472534, "pid": 11544, "hostname": "DESKTOP-6E08LRQ", "node_ip": "127.0.0.1", "config": {"SI_gen_mult": 1.1608267138663855, "SI_gen_fill": 0, "SI_gen_neck": "wide", "SI_gen_z_dim": 1368, "SI_pad_mode": "zeros", "SI_dropout": false, "SI_exp_kernel": 4, "SI_gen_hidden_dim": 20, "SI_skip_mode": "conv", "SI_stats_criterion": -1, "SI_moment_1_fraction": -1, "SI_alpha_min": -1, "SI_half_life_examples": -1, "SI_disc_hidden_dim": 1, "SI_disc_patchGAN": 1, "SI_disc_lr": 1, "SI_disc_b1": 1, "SI_disc_b2": 1, "SI_disc_adv_criterion": 1, "SI_normalize": false, "SI_fixedScale": 1, "SI_learnedScale_init": 16.17836037187811, "SI_output_scale_lr_mult": 2.4740060905127015, "SI_layer_norm": "instance", "SI_gen_final_activ": null, "batch_base2_exponent": 5, "gen_lr": 0.002252812073496261, "gen_b1": 0.3780182972970298, "gen_b2": 0.32535018061489646, "sup_base_criterion": "MSELoss", "IS_disc_hidden_dim": 1, "IS_disc_patchGAN": 1, "IS_disc_lr": 1, "IS_disc_b1": 1, "IS_disc_b2": 1, "IS_disc_adv_criterion": 1, "network_type": "ACT", "train_SI": true, "gen_image_size": 180, "gen_sino_size": 288, "gen_image_channels": 1, "gen_sino_channels": 3}, "time_since_restore": 87.49279737472534, "iterations_since_restore": 20}
{"MSE": 75.39137956500053, "SSIM": 0.7897353634471074, "example_num": 21504, "batch_step": 672, "epoch": 1, "timestamp": 1773552989, "checkpoint_dir_name": null, "done": false, "training_iteration": 21, "trial_id": "76e49193", "date": "2026-03-15_00-36-29", "time_this_iter_s": 4.139199256896973, "time_total_s": 91.63199663162231, "pid": 11544, "hostname": "DESKTOP-6E08LRQ", "node_ip": "127.0.0.1", "config": {"SI_gen_mult": 1.1608267138663855, "SI_gen_fill": 0, "SI_gen_neck": "wide", "SI_gen_z_dim": 1368, "SI_pad_mode": "zeros", "SI_dropout": false, "SI_exp_kernel": 4, "SI_gen_hidden_dim": 20, "SI_skip_mode": "conv", "SI_stats_criterion": -1, "SI_moment_1_fraction": -1, "SI_alpha_min": -1, "SI_half_life_examples": -1, "SI_disc_hidden_dim": 1, "SI_disc_patchGAN": 1, "SI_disc_lr": 1, "SI_disc_b1": 1, "SI_disc_b2": 1, "SI_disc_adv_criterion": 1, "SI_normalize": false, "SI_fixedScale": 1, "SI_learnedScale_init": 16.17836037187811, "SI_output_scale_lr_mult": 2.4740060905127015, "SI_layer_norm": "instance", "SI_gen_final_activ": null, "batch_base2_exponent": 5, "gen_lr": 0.002252812073496261, "gen_b1": 0.3780182972970298, "gen_b2": 0.32535018061489646, "sup_base_criterion": "MSELoss", "IS_disc_hidden_dim": 1, "IS_disc_patchGAN": 1, "IS_disc_lr": 1, "IS_disc_b1": 1, "IS_disc_b2": 1, "IS_disc_adv_criterion": 1, "network_type": "ACT", "train_SI": true, "gen_image_size": 180, "gen_sino_size": 288, "gen_image_channels": 1, "gen_sino_channels": 3}, "time_since_restore": 91.63199663162231, "iterations_since_restore": 21}
{"MSE": 87.14942361414433, "SSIM": 0.7930571234319359, "example_num": 22528, "batch_step": 704, "epoch": 1, "timestamp": 1773552994, "checkpoint_dir_name": null, "done": false, "training_iteration": 22, "trial_id": "76e49193", "date": "2026-03-15_00-36-34", "time_this_iter_s": 4.818711996078491, "time_total_s": 96.4507086277008, "pid": 11544, "hostname": "DESKTOP-6E08LRQ", "node_ip": "127.0.0.1", "config": {"SI_gen_mult": 1.1608267138663855, "SI_gen_fill": 0, "SI_gen_neck": "wide", "SI_gen_z_dim": 1368, "SI_pad_mode": "zeros", "SI_dropout": false, "SI_exp_kernel": 4, "SI_gen_hidden_dim": 20, "SI_skip_mode": "conv", "SI_stats_criterion": -1, "SI_moment_1_fraction": -1, "SI_alpha_min": -1, "SI_half_life_examples": -1, "SI_disc_hidden_dim": 1, "SI_disc_patchGAN": 1, "SI_disc_lr": 1, "SI_disc_b1": 1, "SI_disc_b2": 1, "SI_disc_adv_criterion": 1, "SI_normalize": false, "SI_fixedScale": 1, "SI_learnedScale_init": 16.17836037187811, "SI_output_scale_lr_mult": 2.4740060905127015, "SI_layer_norm": "instance", "SI_gen_final_activ": null, "batch_base2_exponent": 5, "gen_lr": 0.002252812073496261, "gen_b1": 0.3780182972970298, "gen_b2": 0.32535018061489646, "sup_base_criterion": "MSELoss", "IS_disc_hidden_dim": 1, "IS_disc_patchGAN": 1, "IS_disc_lr": 1, "IS_disc_b1": 1, "IS_disc_b2": 1, "IS_disc_adv_criterion": 1, "network_type": "ACT", "train_SI": true, "gen_image_size": 180, "gen_sino_size": 288, "gen_image_channels": 1, "gen_sino_channels": 3}, "time_since_restore": 96.4507086277008, "iterations_since_restore": 22}
{"MSE": 69.02395549416542, "SSIM": 0.7870941161090741, "example_num": 23552, "batch_step": 736, "epoch": 1, "timestamp": 1773552998, "checkpoint_dir_name": null, "done": false, "training_iteration": 23, "trial_id": "76e49193", "date": "2026-03-15_00-36-38", "time_this_iter_s": 3.7384896278381348, "time_total_s": 100.18919825553894, "pid": 11544, "hostname": "DESKTOP-6E08LRQ", "node_ip": "127.0.0.1", "config": {"SI_gen_mult": 1.1608267138663855, "SI_gen_fill": 0, "SI_gen_neck": "wide", "SI_gen_z_dim": 1368, "SI_pad_mode": "zeros", "SI_dropout": false, "SI_exp_kernel": 4, "SI_gen_hidden_dim": 20, "SI_skip_mode": "conv", "SI_stats_criterion": -1, "SI_moment_1_fraction": -1, "SI_alpha_min": -1, "SI_half_life_examples": -1, "SI_disc_hidden_dim": 1, "SI_disc_patchGAN": 1, "SI_disc_lr": 1, "SI_disc_b1": 1, "SI_disc_b2": 1, "SI_disc_adv_criterion": 1, "SI_normalize": false, "SI_fixedScale": 1, "SI_learnedScale_init": 16.17836037187811, "SI_output_scale_lr_mult": 2.4740060905127015, "SI_layer_norm": "instance", "SI_gen_final_activ": null, "batch_base2_exponent": 5, "gen_lr": 0.002252812073496261, "gen_b1": 0.3780182972970298, "gen_b2": 0.32535018061489646, "sup_base_criterion": "MSELoss", "IS_disc_hidden_dim": 1, "IS_disc_patchGAN": 1, "IS_disc_lr": 1, "IS_disc_b1": 1, "IS_disc_b2": 1, "IS_disc_adv_criterion": 1, "network_type": "ACT", "train_SI": true, "gen_image_size": 180, "gen_sino_size": 288, "gen_image_channels": 1, "gen_sino_channels": 3}, "time_since_restore": 100.18919825553894, "iterations_since_restore": 23}
{"MSE": 90.00164436548948, "SSIM": 0.76317806285806, "example_num": 24576, "batch_step": 768, "epoch": 1, "timestamp": 1773553001, "checkpoint_dir_name": null, "done": false, "training_iteration": 24, "trial_id": "76e49193", "date": "2026-03-15_00-36-41", "time_this_iter_s": 3.6477787494659424, "time_total_s": 103.83697700500488, "pid": 11544, "hostname": "DESKTOP-6E08LRQ", "node_ip": "127.0.0.1", "config": {"SI_gen_mult": 1.1608267138663855, "SI_gen_fill": 0, "SI_gen_neck": "wide", "SI_gen_z_dim": 1368, "SI_pad_mode": "zeros", "SI_dropout": false, "SI_exp_kernel": 4, "SI_gen_hidden_dim": 20, "SI_skip_mode": "conv", "SI_stats_criterion": -1, "SI_moment_1_fraction": -1, "SI_alpha_min": -1, "SI_half_life_examples": -1, "SI_disc_hidden_dim": 1, "SI_disc_patchGAN": 1, "SI_disc_lr": 1, "SI_disc_b1": 1, "SI_disc_b2": 1, "SI_disc_adv_criterion": 1, "SI_normalize": false, "SI_fixedScale": 1, "SI_learnedScale_init": 16.17836037187811, "SI_output_scale_lr_mult": 2.4740060905127015, "SI_layer_norm": "instance", "SI_gen_final_activ": null, "batch_base2_exponent": 5, "gen_lr": 0.002252812073496261, "gen_b1": 0.3780182972970298, "gen_b2": 0.32535018061489646, "sup_base_criterion": "MSELoss", "IS_disc_hidden_dim": 1, "IS_disc_patchGAN": 1, "IS_disc_lr": 1, "IS_disc_b1": 1, "IS_disc_b2": 1, "IS_disc_adv_criterion": 1, "network_type": "ACT", "train_SI": true, "gen_image_size": 180, "gen_sino_size": 288, "gen_image_channels": 1, "gen_sino_channels": 3}, "time_since_restore": 103.83697700500488, "iterations_since_restore": 24}
{"MSE": 82.28213854134083, "SSIM": 0.7816598603967577, "example_num": 25600, "batch_step": 800, "epoch": 1, "timestamp": 1773553006, "checkpoint_dir_name": null, "done": false, "training_iteration": 25, "trial_id": "76e49193", "date": "2026-03-15_00-36-46", "time_this_iter_s": 4.182237863540649, "time_total_s": 108.01921486854553, "pid": 11544, "hostname": "DESKTOP-6E08LRQ", "node_ip": "127.0.0.1", "config": {"SI_gen_mult": 1.1608267138663855, "SI_gen_fill": 0, "SI_gen_neck": "wide", "SI_gen_z_dim": 1368, "SI_pad_mode": "zeros", "SI_dropout": false, "SI_exp_kernel": 4, "SI_gen_hidden_dim": 20, "SI_skip_mode": "conv", "SI_stats_criterion": -1, "SI_moment_1_fraction": -1, "SI_alpha_min": -1, "SI_half_life_examples": -1, "SI_disc_hidden_dim": 1, "SI_disc_patchGAN": 1, "SI_disc_lr": 1, "SI_disc_b1": 1, "SI_disc_b2": 1, "SI_disc_adv_criterion": 1, "SI_normalize": false, "SI_fixedScale": 1, "SI_learnedScale_init": 16.17836037187811, "SI_output_scale_lr_mult": 2.4740060905127015, "SI_layer_norm": "instance", "SI_gen_final_activ": null, "batch_base2_exponent": 5, "gen_lr": 0.002252812073496261, "gen_b1": 0.3780182972970298, "gen_b2": 0.32535018061489646, "sup_base_criterion": "MSELoss", "IS_disc_hidden_dim": 1, "IS_disc_patchGAN": 1, "IS_disc_lr": 1, "IS_disc_b1": 1, "IS_disc_b2": 1, "IS_disc_adv_criterion": 1, "network_type": "ACT", "train_SI": true, "gen_image_size": 180, "gen_sino_size": 288, "gen_image_channels": 1, "gen_sino_channels": 3}, "time_since_restore": 108.01921486854553, "iterations_since_restore": 25}
{"MSE": 57.4964205622673, "SSIM": 0.7933050026185811, "example_num": 26624, "batch_step": 832, "epoch": 1, "timestamp": 1773553010, "checkpoint_dir_name": null, "done": false, "training_iteration": 26, "trial_id": "76e49193", "date": "2026-03-15_00-36-50", "time_this_iter_s": 4.092127323150635, "time_total_s": 112.11134219169617, "pid": 11544, "hostname": "DESKTOP-6E08LRQ", "node_ip": "127.0.0.1", "config": {"SI_gen_mult": 1.1608267138663855, "SI_gen_fill": 0, "SI_gen_neck": "wide", "SI_gen_z_dim": 1368, "SI_pad_mode": "zeros", "SI_dropout": false, "SI_exp_kernel": 4, "SI_gen_hidden_dim": 20, "SI_skip_mode": "conv", "SI_stats_criterion": -1, "SI_moment_1_fraction": -1, "SI_alpha_min": -1, "SI_half_life_examples": -1, "SI_disc_hidden_dim": 1, "SI_disc_patchGAN": 1, "SI_disc_lr": 1, "SI_disc_b1": 1, "SI_disc_b2": 1, "SI_disc_adv_criterion": 1, "SI_normalize": false, "SI_fixedScale": 1, "SI_learnedScale_init": 16.17836037187811, "SI_output_scale_lr_mult": 2.4740060905127015, "SI_layer_norm": "instance", "SI_gen_final_activ": null, "batch_base2_exponent": 5, "gen_lr": 0.002252812073496261, "gen_b1": 0.3780182972970298, "gen_b2": 0.32535018061489646, "sup_base_criterion": "MSELoss", "IS_disc_hidden_dim": 1, "IS_disc_patchGAN": 1, "IS_disc_lr": 1, "IS_disc_b1": 1, "IS_disc_b2": 1, "IS_disc_adv_criterion": 1, "network_type": "ACT", "train_SI": true, "gen_image_size": 180, "gen_sino_size": 288, "gen_image_channels": 1, "gen_sino_channels": 3}, "time_since_restore": 112.11134219169617, "iterations_since_restore": 26}
{"MSE": 65.49569037556648, "SSIM": 0.8023886347655207, "example_num": 27648, "batch_step": 864, "epoch": 1, "timestamp": 1773553014, "checkpoint_dir_name": null, "done": false, "training_iteration": 27, "trial_id": "76e49193", "date": "2026-03-15_00-36-54", "time_this_iter_s": 4.536075115203857, "time_total_s": 116.64741730690002, "pid": 11544, "hostname": "DESKTOP-6E08LRQ", "node_ip": "127.0.0.1", "config": {"SI_gen_mult": 1.1608267138663855, "SI_gen_fill": 0, "SI_gen_neck": "wide", "SI_gen_z_dim": 1368, "SI_pad_mode": "zeros", "SI_dropout": false, "SI_exp_kernel": 4, "SI_gen_hidden_dim": 20, "SI_skip_mode": "conv", "SI_stats_criterion": -1, "SI_moment_1_fraction": -1, "SI_alpha_min": -1, "SI_half_life_examples": -1, "SI_disc_hidden_dim": 1, "SI_disc_patchGAN": 1, "SI_disc_lr": 1, "SI_disc_b1": 1, "SI_disc_b2": 1, "SI_disc_adv_criterion": 1, "SI_normalize": false, "SI_fixedScale": 1, "SI_learnedScale_init": 16.17836037187811, "SI_output_scale_lr_mult": 2.4740060905127015, "SI_layer_norm": "instance", "SI_gen_final_activ": null, "batch_base2_exponent": 5, "gen_lr": 0.002252812073496261, "gen_b1": 0.3780182972970298, "gen_b2": 0.32535018061489646, "sup_base_criterion": "MSELoss", "IS_disc_hidden_dim": 1, "IS_disc_patchGAN": 1, "IS_disc_lr": 1, "IS_disc_b1": 1, "IS_disc_b2": 1, "IS_disc_adv_criterion": 1, "network_type": "ACT", "train_SI": true, "gen_image_size": 180, "gen_sino_size": 288, "gen_image_channels": 1, "gen_sino_channels": 3}, "time_since_restore": 116.64741730690002, "iterations_since_restore": 27}
{"MSE": 67.93445931375027, "SSIM": 0.7976080304943025, "example_num": 28672, "batch_step": 896, "epoch": 1, "timestamp": 1773553018, "checkpoint_dir_name": null, "done": false, "training_iteration": 28, "trial_id": "76e49193", "date": "2026-03-15_00-36-58", "time_this_iter_s": 3.724005937576294, "time_total_s": 120.37142324447632, "pid": 11544, "hostname": "DESKTOP-6E08LRQ", "node_ip": "127.0.0.1", "config": {"SI_gen_mult": 1.1608267138663855, "SI_gen_fill": 0, "SI_gen_neck": "wide", "SI_gen_z_dim": 1368, "SI_pad_mode": "zeros", "SI_dropout": false, "SI_exp_kernel": 4, "SI_gen_hidden_dim": 20, "SI_skip_mode": "conv", "SI_stats_criterion": -1, "SI_moment_1_fraction": -1, "SI_alpha_min": -1, "SI_half_life_examples": -1, "SI_disc_hidden_dim": 1, "SI_disc_patchGAN": 1, "SI_disc_lr": 1, "SI_disc_b1": 1, "SI_disc_b2": 1, "SI_disc_adv_criterion": 1, "SI_normalize": false, "SI_fixedScale": 1, "SI_learnedScale_init": 16.17836037187811, "SI_output_scale_lr_mult": 2.4740060905127015, "SI_layer_norm": "instance", "SI_gen_final_activ": null, "batch_base2_exponent": 5, "gen_lr": 0.002252812073496261, "gen_b1": 0.3780182972970298, "gen_b2": 0.32535018061489646, "sup_base_criterion": "MSELoss", "IS_disc_hidden_dim": 1, "IS_disc_patchGAN": 1, "IS_disc_lr": 1, "IS_disc_b1": 1, "IS_disc_b2": 1, "IS_disc_adv_criterion": 1, "network_type": "ACT", "train_SI": true, "gen_image_size": 180, "gen_sino_size": 288, "gen_image_channels": 1, "gen_sino_channels": 3}, "time_since_restore": 120.37142324447632, "iterations_since_restore": 28}
{"MSE": 81.8616148903966, "SSIM": 0.7778288318077102, "example_num": 29696, "batch_step": 928, "epoch": 1, "timestamp": 1773553022, "checkpoint_dir_name": null, "done": false, "training_iteration": 29, "trial_id": "76e49193", "date": "2026-03-15_00-37-02", "time_this_iter_s": 4.049822568893433, "time_total_s": 124.42124581336975, "pid": 11544, "hostname": "DESKTOP-6E08LRQ", "node_ip": "127.0.0.1", "config": {"SI_gen_mult": 1.1608267138663855, "SI_gen_fill": 0, "SI_gen_neck": "wide", "SI_gen_z_dim": 1368, "SI_pad_mode": "zeros", "SI_dropout": false, "SI_exp_kernel": 4, "SI_gen_hidden_dim": 20, "SI_skip_mode": "conv", "SI_stats_criterion": -1, "SI_moment_1_fraction": -1, "SI_alpha_min": -1, "SI_half_life_examples": -1, "SI_disc_hidden_dim": 1, "SI_disc_patchGAN": 1, "SI_disc_lr": 1, "SI_disc_b1": 1, "SI_disc_b2": 1, "SI_disc_adv_criterion": 1, "SI_normalize": false, "SI_fixedScale": 1, "SI_learnedScale_init": 16.17836037187811, "SI_output_scale_lr_mult": 2.4740060905127015, "SI_layer_norm": "instance", "SI_gen_final_activ": null, "batch_base2_exponent": 5, "gen_lr": 0.002252812073496261, "gen_b1": 0.3780182972970298, "gen_b2": 0.32535018061489646, "sup_base_criterion": "MSELoss", "IS_disc_hidden_dim": 1, "IS_disc_patchGAN": 1, "IS_disc_lr": 1, "IS_disc_b1": 1, "IS_disc_b2": 1, "IS_disc_adv_criterion": 1, "network_type": "ACT", "train_SI": true, "gen_image_size": 180, "gen_sino_size": 288, "gen_image_channels": 1, "gen_sino_channels": 3}, "time_since_restore": 124.42124581336975, "iterations_since_restore": 29}
{"MSE": 65.52055330574512, "SSIM": 0.810770362848416, "example_num": 30720, "batch_step": 960, "epoch": 1, "timestamp": 1773553026, "checkpoint_dir_name": null, "done": false, "training_iteration": 30, "trial_id": "76e49193", "date": "2026-03-15_00-37-06", "time_this_iter_s": 3.92207670211792, "time_total_s": 128.34332251548767, "pid": 11544, "hostname": "DESKTOP-6E08LRQ", "node_ip": "127.0.0.1", "config": {"SI_gen_mult": 1.1608267138663855, "SI_gen_fill": 0, "SI_gen_neck": "wide", "SI_gen_z_dim": 1368, "SI_pad_mode": "zeros", "SI_dropout": false, "SI_exp_kernel": 4, "SI_gen_hidden_dim": 20, "SI_skip_mode": "conv", "SI_stats_criterion": -1, "SI_moment_1_fraction": -1, "SI_alpha_min": -1, "SI_half_life_examples": -1, "SI_disc_hidden_dim": 1, "SI_disc_patchGAN": 1, "SI_disc_lr": 1, "SI_disc_b1": 1, "SI_disc_b2": 1, "SI_disc_adv_criterion": 1, "SI_normalize": false, "SI_fixedScale": 1, "SI_learnedScale_init": 16.17836037187811, "SI_output_scale_lr_mult": 2.4740060905127015, "SI_layer_norm": "instance", "SI_gen_final_activ": null, "batch_base2_exponent": 5, "gen_lr": 0.002252812073496261, "gen_b1": 0.3780182972970298, "gen_b2": 0.32535018061489646, "sup_base_criterion": "MSELoss", "IS_disc_hidden_dim": 1, "IS_disc_patchGAN": 1, "IS_disc_lr": 1, "IS_disc_b1": 1, "IS_disc_b2": 1, "IS_disc_adv_criterion": 1, "network_type": "ACT", "train_SI": true, "gen_image_size": 180, "gen_sino_size": 288, "gen_image_channels": 1, "gen_sino_channels": 3}, "time_since_restore": 128.34332251548767, "iterations_since_restore": 30}
{"MSE": 87.78895065188408, "SSIM": 0.8037470155395567, "example_num": 31744, "batch_step": 992, "epoch": 1, "timestamp": 1773553030, "checkpoint_dir_name": null, "done": false, "training_iteration": 31, "trial_id": "76e49193", "date": "2026-03-15_00-37-10", "time_this_iter_s": 3.6690316200256348, "time_total_s": 132.0123541355133, "pid": 11544, "hostname": "DESKTOP-6E08LRQ", "node_ip": "127.0.0.1", "config": {"SI_gen_mult": 1.1608267138663855, "SI_gen_fill": 0, "SI_gen_neck": "wide", "SI_gen_z_dim": 1368, "SI_pad_mode": "zeros", "SI_dropout": false, "SI_exp_kernel": 4, "SI_gen_hidden_dim": 20, "SI_skip_mode": "conv", "SI_stats_criterion": -1, "SI_moment_1_fraction": -1, "SI_alpha_min": -1, "SI_half_life_examples": -1, "SI_disc_hidden_dim": 1, "SI_disc_patchGAN": 1, "SI_disc_lr": 1, "SI_disc_b1": 1, "SI_disc_b2": 1, "SI_disc_adv_criterion": 1, "SI_normalize": false, "SI_fixedScale": 1, "SI_learnedScale_init": 16.17836037187811, "SI_output_scale_lr_mult": 2.4740060905127015, "SI_layer_norm": "instance", "SI_gen_final_activ": null, "batch_base2_exponent": 5, "gen_lr": 0.002252812073496261, "gen_b1": 0.3780182972970298, "gen_b2": 0.32535018061489646, "sup_base_criterion": "MSELoss", "IS_disc_hidden_dim": 1, "IS_disc_patchGAN": 1, "IS_disc_lr": 1, "IS_disc_b1": 1, "IS_disc_b2": 1, "IS_disc_adv_criterion": 1, "network_type": "ACT", "train_SI": true, "gen_image_size": 180, "gen_sino_size": 288, "gen_image_channels": 1, "gen_sino_channels": 3}, "time_since_restore": 132.0123541355133, "iterations_since_restore": 31}
{"MSE": 60.89315712451935, "SSIM": 0.8160799613688141, "example_num": 32768, "batch_step": 1024, "epoch": 1, "timestamp": 1773553034, "checkpoint_dir_name": null, "done": false, "training_iteration": 32, "trial_id": "76e49193", "date": "2026-03-15_00-37-14", "time_this_iter_s": 4.4111411571502686, "time_total_s": 136.42349529266357, "pid": 11544, "hostname": "DESKTOP-6E08LRQ", "node_ip": "127.0.0.1", "config": {"SI_gen_mult": 1.1608267138663855, "SI_gen_fill": 0, "SI_gen_neck": "wide", "SI_gen_z_dim": 1368, "SI_pad_mode": "zeros", "SI_dropout": false, "SI_exp_kernel": 4, "SI_gen_hidden_dim": 20, "SI_skip_mode": "conv", "SI_stats_criterion": -1, "SI_moment_1_fraction": -1, "SI_alpha_min": -1, "SI_half_life_examples": -1, "SI_disc_hidden_dim": 1, "SI_disc_patchGAN": 1, "SI_disc_lr": 1, "SI_disc_b1": 1, "SI_disc_b2": 1, "SI_disc_adv_criterion": 1, "SI_normalize": false, "SI_fixedScale": 1, "SI_learnedScale_init": 16.17836037187811, "SI_output_scale_lr_mult": 2.4740060905127015, "SI_layer_norm": "instance", "SI_gen_final_activ": null, "batch_base2_exponent": 5, "gen_lr": 0.002252812073496261, "gen_b1": 0.3780182972970298, "gen_b2": 0.32535018061489646, "sup_base_criterion": "MSELoss", "IS_disc_hidden_dim": 1, "IS_disc_patchGAN": 1, "IS_disc_lr": 1, "IS_disc_b1": 1, "IS_disc_b2": 1, "IS_disc_adv_criterion": 1, "network_type": "ACT", "train_SI": true, "gen_image_size": 180, "gen_sino_size": 288, "gen_image_channels": 1, "gen_sino_channels": 3}, "time_since_restore": 136.42349529266357, "iterations_since_restore": 32}
{"MSE": 73.60685747861862, "SSIM": 0.8009886839427054, "example_num": 33792, "batch_step": 1056, "epoch": 1, "timestamp": 1773553038, "checkpoint_dir_name": null, "done": false, "training_iteration": 33, "trial_id": "76e49193", "date": "2026-03-15_00-37-18", "time_this_iter_s": 3.7496285438537598, "time_total_s": 140.17312383651733, "pid": 11544, "hostname": "DESKTOP-6E08LRQ", "node_ip": "127.0.0.1", "config": {"SI_gen_mult": 1.1608267138663855, "SI_gen_fill": 0, "SI_gen_neck": "wide", "SI_gen_z_dim": 1368, "SI_pad_mode": "zeros", "SI_dropout": false, "SI_exp_kernel": 4, "SI_gen_hidden_dim": 20, "SI_skip_mode": "conv", "SI_stats_criterion": -1, "SI_moment_1_fraction": -1, "SI_alpha_min": -1, "SI_half_life_examples": -1, "SI_disc_hidden_dim": 1, "SI_disc_patchGAN": 1, "SI_disc_lr": 1, "SI_disc_b1": 1, "SI_disc_b2": 1, "SI_disc_adv_criterion": 1, "SI_normalize": false, "SI_fixedScale": 1, "SI_learnedScale_init": 16.17836037187811, "SI_output_scale_lr_mult": 2.4740060905127015, "SI_layer_norm": "instance", "SI_gen_final_activ": null, "batch_base2_exponent": 5, "gen_lr": 0.002252812073496261, "gen_b1": 0.3780182972970298, "gen_b2": 0.32535018061489646, "sup_base_criterion": "MSELoss", "IS_disc_hidden_dim": 1, "IS_disc_patchGAN": 1, "IS_disc_lr": 1, "IS_disc_b1": 1, "IS_disc_b2": 1, "IS_disc_adv_criterion": 1, "network_type": "ACT", "train_SI": true, "gen_image_size": 180, "gen_sino_size": 288, "gen_image_channels": 1, "gen_sino_channels": 3}, "time_since_restore": 140.17312383651733, "iterations_since_restore": 33}
{"MSE": 83.53477085195482, "SSIM": 0.7141629828256555, "example_num": 34816, "batch_step": 1088, "epoch": 1, "timestamp": 1773553042, "checkpoint_dir_name": null, "done": false, "training_iteration": 34, "trial_id": "76e49193", "date": "2026-03-15_00-37-22", "time_this_iter_s": 3.961764097213745, "time_total_s": 144.13488793373108, "pid": 11544, "hostname": "DESKTOP-6E08LRQ", "node_ip": "127.0.0.1", "config": {"SI_gen_mult": 1.1608267138663855, "SI_gen_fill": 0, "SI_gen_neck": "wide", "SI_gen_z_dim": 1368, "SI_pad_mode": "zeros", "SI_dropout": false, "SI_exp_kernel": 4, "SI_gen_hidden_dim": 20, "SI_skip_mode": "conv", "SI_stats_criterion": -1, "SI_moment_1_fraction": -1, "SI_alpha_min": -1, "SI_half_life_examples": -1, "SI_disc_hidden_dim": 1, "SI_disc_patchGAN": 1, "SI_disc_lr": 1, "SI_disc_b1": 1, "SI_disc_b2": 1, "SI_disc_adv_criterion": 1, "SI_normalize": false, "SI_fixedScale": 1, "SI_learnedScale_init": 16.17836037187811, "SI_output_scale_lr_mult": 2.4740060905127015, "SI_layer_norm": "instance", "SI_gen_final_activ": null, "batch_base2_exponent": 5, "gen_lr": 0.002252812073496261, "gen_b1": 0.3780182972970298, "gen_b2": 0.32535018061489646, "sup_base_criterion": "MSELoss", "IS_disc_hidden_dim": 1, "IS_disc_patchGAN": 1, "IS_disc_lr": 1, "IS_disc_b1": 1, "IS_disc_b2": 1, "IS_disc_adv_criterion": 1, "network_type": "ACT", "train_SI": true, "gen_image_size": 180, "gen_sino_size": 288, "gen_image_channels": 1, "gen_sino_channels": 3}, "time_since_restore": 144.13488793373108, "iterations_since_restore": 34}
{"MSE": 79.82391400635242, "SSIM": 0.7982056092005223, "example_num": 35840, "batch_step": 1120, "epoch": 2, "timestamp": 1773553046, "checkpoint_dir_name": null, "done": false, "training_iteration": 35, "trial_id": "76e49193", "date": "2026-03-15_00-37-26", "time_this_iter_s": 4.126033544540405, "time_total_s": 148.26092147827148, "pid": 11544, "hostname": "DESKTOP-6E08LRQ", "node_ip": "127.0.0.1", "config": {"SI_gen_mult": 1.1608267138663855, "SI_gen_fill": 0, "SI_gen_neck": "wide", "SI_gen_z_dim": 1368, "SI_pad_mode": "zeros", "SI_dropout": false, "SI_exp_kernel": 4, "SI_gen_hidden_dim": 20, "SI_skip_mode": "conv", "SI_stats_criterion": -1, "SI_moment_1_fraction": -1, "SI_alpha_min": -1, "SI_half_life_examples": -1, "SI_disc_hidden_dim": 1, "SI_disc_patchGAN": 1, "SI_disc_lr": 1, "SI_disc_b1": 1, "SI_disc_b2": 1, "SI_disc_adv_criterion": 1, "SI_normalize": false, "SI_fixedScale": 1, "SI_learnedScale_init": 16.17836037187811, "SI_output_scale_lr_mult": 2.4740060905127015, "SI_layer_norm": "instance", "SI_gen_final_activ": null, "batch_base2_exponent": 5, "gen_lr": 0.002252812073496261, "gen_b1": 0.3780182972970298, "gen_b2": 0.32535018061489646, "sup_base_criterion": "MSELoss", "IS_disc_hidden_dim": 1, "IS_disc_patchGAN": 1, "IS_disc_lr": 1, "IS_disc_b1": 1, "IS_disc_b2": 1, "IS_disc_adv_criterion": 1, "network_type": "ACT", "train_SI": true, "gen_image_size": 180, "gen_sino_size": 288, "gen_image_channels": 1, "gen_sino_channels": 3}, "time_since_restore": 148.26092147827148, "iterations_since_restore": 35}
{"MSE": 78.35341531038284, "SSIM": 0.7911488022655249, "example_num": 36864, "batch_step": 1152, "epoch": 2, "timestamp": 1773553049, "checkpoint_dir_name": null, "done": false, "training_iteration": 36, "trial_id": "76e49193", "date": "2026-03-15_00-37-29", "time_this_iter_s": 3.6239724159240723, "time_total_s": 151.88489389419556, "pid": 11544, "hostname": "DESKTOP-6E08LRQ", "node_ip": "127.0.0.1", "config": {"SI_gen_mult": 1.1608267138663855, "SI_gen_fill": 0, "SI_gen_neck": "wide", "SI_gen_z_dim": 1368, "SI_pad_mode": "zeros", "SI_dropout": false, "SI_exp_kernel": 4, "SI_gen_hidden_dim": 20, "SI_skip_mode": "conv", "SI_stats_criterion": -1, "SI_moment_1_fraction": -1, "SI_alpha_min": -1, "SI_half_life_examples": -1, "SI_disc_hidden_dim": 1, "SI_disc_patchGAN": 1, "SI_disc_lr": 1, "SI_disc_b1": 1, "SI_disc_b2": 1, "SI_disc_adv_criterion": 1, "SI_normalize": false, "SI_fixedScale": 1, "SI_learnedScale_init": 16.17836037187811, "SI_output_scale_lr_mult": 2.4740060905127015, "SI_layer_norm": "instance", "SI_gen_final_activ": null, "batch_base2_exponent": 5, "gen_lr": 0.002252812073496261, "gen_b1": 0.3780182972970298, "gen_b2": 0.32535018061489646, "sup_base_criterion": "MSELoss", "IS_disc_hidden_dim": 1, "IS_disc_patchGAN": 1, "IS_disc_lr": 1, "IS_disc_b1": 1, "IS_disc_b2": 1, "IS_disc_adv_criterion": 1, "network_type": "ACT", "train_SI": true, "gen_image_size": 180, "gen_sino_size": 288, "gen_image_channels": 1, "gen_sino_channels": 3}, "time_since_restore": 151.88489389419556, "iterations_since_restore": 36}
{"MSE": 56.72971898317337, "SSIM": 0.8059044159017503, "example_num": 37888, "batch_step": 1184, "epoch": 2, "timestamp": 1773553054, "checkpoint_dir_name": null, "done": false, "training_iteration": 37, "trial_id": "76e49193", "date": "2026-03-15_00-37-34", "time_this_iter_s": 4.393506050109863, "time_total_s": 156.27839994430542, "pid": 11544, "hostname": "DESKTOP-6E08LRQ", "node_ip": "127.0.0.1", "config": {"SI_gen_mult": 1.1608267138663855, "SI_gen_fill": 0, "SI_gen_neck": "wide", "SI_gen_z_dim": 1368, "SI_pad_mode": "zeros", "SI_dropout": false, "SI_exp_kernel": 4, "SI_gen_hidden_dim": 20, "SI_skip_mode": "conv", "SI_stats_criterion": -1, "SI_moment_1_fraction": -1, "SI_alpha_min": -1, "SI_half_life_examples": -1, "SI_disc_hidden_dim": 1, "SI_disc_patchGAN": 1, "SI_disc_lr": 1, "SI_disc_b1": 1, "SI_disc_b2": 1, "SI_disc_adv_criterion": 1, "SI_normalize": false, "SI_fixedScale": 1, "SI_learnedScale_init": 16.17836037187811, "SI_output_scale_lr_mult": 2.4740060905127015, "SI_layer_norm": "instance", "SI_gen_final_activ": null, "batch_base2_exponent": 5, "gen_lr": 0.002252812073496261, "gen_b1": 0.3780182972970298, "gen_b2": 0.32535018061489646, "sup_base_criterion": "MSELoss", "IS_disc_hidden_dim": 1, "IS_disc_patchGAN": 1, "IS_disc_lr": 1, "IS_disc_b1": 1, "IS_disc_b2": 1, "IS_disc_adv_criterion": 1, "network_type": "ACT", "train_SI": true, "gen_image_size": 180, "gen_sino_size": 288, "gen_image_channels": 1, "gen_sino_channels": 3}, "time_since_restore": 156.27839994430542, "iterations_since_restore": 37}
{"MSE": 71.79977465420961, "SSIM": 0.7955371397547424, "example_num": 38912, "batch_step": 1216, "epoch": 2, "timestamp": 1773553058, "checkpoint_dir_name": null, "done": false, "training_iteration": 38, "trial_id": "76e49193", "date": "2026-03-15_00-37-38", "time_this_iter_s": 3.9849069118499756, "time_total_s": 160.2633068561554, "pid": 11544, "hostname": "DESKTOP-6E08LRQ", "node_ip": "127.0.0.1", "config": {"SI_gen_mult": 1.1608267138663855, "SI_gen_fill": 0, "SI_gen_neck": "wide", "SI_gen_z_dim": 1368, "SI_pad_mode": "zeros", "SI_dropout": false, "SI_exp_kernel": 4, "SI_gen_hidden_dim": 20, "SI_skip_mode": "conv", "SI_stats_criterion": -1, "SI_moment_1_fraction": -1, "SI_alpha_min": -1, "SI_half_life_examples": -1, "SI_disc_hidden_dim": 1, "SI_disc_patchGAN": 1, "SI_disc_lr": 1, "SI_disc_b1": 1, "SI_disc_b2": 1, "SI_disc_adv_criterion": 1, "SI_normalize": false, "SI_fixedScale": 1, "SI_learnedScale_init": 16.17836037187811, "SI_output_scale_lr_mult": 2.4740060905127015, "SI_layer_norm": "instance", "SI_gen_final_activ": null, "batch_base2_exponent": 5, "gen_lr": 0.002252812073496261, "gen_b1": 0.3780182972970298, "gen_b2": 0.32535018061489646, "sup_base_criterion": "MSELoss", "IS_disc_hidden_dim": 1, "IS_disc_patchGAN": 1, "IS_disc_lr": 1, "IS_disc_b1": 1, "IS_disc_b2": 1, "IS_disc_adv_criterion": 1, "network_type": "ACT", "train_SI": true, "gen_image_size": 180, "gen_sino_size": 288, "gen_image_channels": 1, "gen_sino_channels": 3}, "time_since_restore": 160.2633068561554, "iterations_since_restore": 38}
{"MSE": 80.59288349747658, "SSIM": 0.8167760514188558, "example_num": 39936, "batch_step": 1248, "epoch": 2, "timestamp": 1773553063, "checkpoint_dir_name": null, "done": false, "training_iteration": 39, "trial_id": "76e49193", "date": "2026-03-15_00-37-43", "time_this_iter_s": 4.7010743618011475, "time_total_s": 164.96438121795654, "pid": 11544, "hostname": "DESKTOP-6E08LRQ", "node_ip": "127.0.0.1", "config": {"SI_gen_mult": 1.1608267138663855, "SI_gen_fill": 0, "SI_gen_neck": "wide", "SI_gen_z_dim": 1368, "SI_pad_mode": "zeros", "SI_dropout": false, "SI_exp_kernel": 4, "SI_gen_hidden_dim": 20, "SI_skip_mode": "conv", "SI_stats_criterion": -1, "SI_moment_1_fraction": -1, "SI_alpha_min": -1, "SI_half_life_examples": -1, "SI_disc_hidden_dim": 1, "SI_disc_patchGAN": 1, "SI_disc_lr": 1, "SI_disc_b1": 1, "SI_disc_b2": 1, "SI_disc_adv_criterion": 1, "SI_normalize": false, "SI_fixedScale": 1, "SI_learnedScale_init": 16.17836037187811, "SI_output_scale_lr_mult": 2.4740060905127015, "SI_layer_norm": "instance", "SI_gen_final_activ": null, "batch_base2_exponent": 5, "gen_lr": 0.002252812073496261, "gen_b1": 0.3780182972970298, "gen_b2": 0.32535018061489646, "sup_base_criterion": "MSELoss", "IS_disc_hidden_dim": 1, "IS_disc_patchGAN": 1, "IS_disc_lr": 1, "IS_disc_b1": 1, "IS_disc_b2": 1, "IS_disc_adv_criterion": 1, "network_type": "ACT", "train_SI": true, "gen_image_size": 180, "gen_sino_size": 288, "gen_image_channels": 1, "gen_sino_channels": 3}, "time_since_restore": 164.96438121795654, "iterations_since_restore": 39}
{"MSE": 80.65300015360117, "SSIM": 0.7995341350324452, "example_num": 40960, "batch_step": 1280, "epoch": 2, "timestamp": 1773553067, "checkpoint_dir_name": null, "done": false, "training_iteration": 40, "trial_id": "76e49193", "date": "2026-03-15_00-37-47", "time_this_iter_s": 4.791000604629517, "time_total_s": 169.75538182258606, "pid": 11544, "hostname": "DESKTOP-6E08LRQ", "node_ip": "127.0.0.1", "config": {"SI_gen_mult": 1.1608267138663855, "SI_gen_fill": 0, "SI_gen_neck": "wide", "SI_gen_z_dim": 1368, "SI_pad_mode": "zeros", "SI_dropout": false, "SI_exp_kernel": 4, "SI_gen_hidden_dim": 20, "SI_skip_mode": "conv", "SI_stats_criterion": -1, "SI_moment_1_fraction": -1, "SI_alpha_min": -1, "SI_half_life_examples": -1, "SI_disc_hidden_dim": 1, "SI_disc_patchGAN": 1, "SI_disc_lr": 1, "SI_disc_b1": 1, "SI_disc_b2": 1, "SI_disc_adv_criterion": 1, "SI_normalize": false, "SI_fixedScale": 1, "SI_learnedScale_init": 16.17836037187811, "SI_output_scale_lr_mult": 2.4740060905127015, "SI_layer_norm": "instance", "SI_gen_final_activ": null, "batch_base2_exponent": 5, "gen_lr": 0.002252812073496261, "gen_b1": 0.3780182972970298, "gen_b2": 0.32535018061489646, "sup_base_criterion": "MSELoss", "IS_disc_hidden_dim": 1, "IS_disc_patchGAN": 1, "IS_disc_lr": 1, "IS_disc_b1": 1, "IS_disc_b2": 1, "IS_disc_adv_criterion": 1, "network_type": "ACT", "train_SI": true, "gen_image_size": 180, "gen_sino_size": 288, "gen_image_channels": 1, "gen_sino_channels": 3}, "time_since_restore": 169.75538182258606, "iterations_since_restore": 40}
{"MSE": 74.30179646611214, "SSIM": 0.7880302669800585, "example_num": 41984, "batch_step": 1312, "epoch": 2, "timestamp": 1773553072, "checkpoint_dir_name": null, "done": false, "training_iteration": 41, "trial_id": "76e49193", "date": "2026-03-15_00-37-52", "time_this_iter_s": 4.29366397857666, "time_total_s": 174.04904580116272, "pid": 11544, "hostname": "DESKTOP-6E08LRQ", "node_ip": "127.0.0.1", "config": {"SI_gen_mult": 1.1608267138663855, "SI_gen_fill": 0, "SI_gen_neck": "wide", "SI_gen_z_dim": 1368, "SI_pad_mode": "zeros", "SI_dropout": false, "SI_exp_kernel": 4, "SI_gen_hidden_dim": 20, "SI_skip_mode": "conv", "SI_stats_criterion": -1, "SI_moment_1_fraction": -1, "SI_alpha_min": -1, "SI_half_life_examples": -1, "SI_disc_hidden_dim": 1, "SI_disc_patchGAN": 1, "SI_disc_lr": 1, "SI_disc_b1": 1, "SI_disc_b2": 1, "SI_disc_adv_criterion": 1, "SI_normalize": false, "SI_fixedScale": 1, "SI_learnedScale_init": 16.17836037187811, "SI_output_scale_lr_mult": 2.4740060905127015, "SI_layer_norm": "instance", "SI_gen_final_activ": null, "batch_base2_exponent": 5, "gen_lr": 0.002252812073496261, "gen_b1": 0.3780182972970298, "gen_b2": 0.32535018061489646, "sup_base_criterion": "MSELoss", "IS_disc_hidden_dim": 1, "IS_disc_patchGAN": 1, "IS_disc_lr": 1, "IS_disc_b1": 1, "IS_disc_b2": 1, "IS_disc_adv_criterion": 1, "network_type": "ACT", "train_SI": true, "gen_image_size": 180, "gen_sino_size": 288, "gen_image_channels": 1, "gen_sino_channels": 3}, "time_since_restore": 174.04904580116272, "iterations_since_restore": 41}
{"MSE": 54.973321944475174, "SSIM": 0.8209397266618907, "example_num": 43008, "batch_step": 1344, "epoch": 2, "timestamp": 1773553076, "checkpoint_dir_name": null, "done": false, "training_iteration": 42, "trial_id": "76e49193", "date": "2026-03-15_00-37-56", "time_this_iter_s": 4.254083633422852, "time_total_s": 178.30312943458557, "pid": 11544, "hostname": "DESKTOP-6E08LRQ", "node_ip": "127.0.0.1", "config": {"SI_gen_mult": 1.1608267138663855, "SI_gen_fill": 0, "SI_gen_neck": "wide", "SI_gen_z_dim": 1368, "SI_pad_mode": "zeros", "SI_dropout": false, "SI_exp_kernel": 4, "SI_gen_hidden_dim": 20, "SI_skip_mode": "conv", "SI_stats_criterion": -1, "SI_moment_1_fraction": -1, "SI_alpha_min": -1, "SI_half_life_examples": -1, "SI_disc_hidden_dim": 1, "SI_disc_patchGAN": 1, "SI_disc_lr": 1, "SI_disc_b1": 1, "SI_disc_b2": 1, "SI_disc_adv_criterion": 1, "SI_normalize": false, "SI_fixedScale": 1, "SI_learnedScale_init": 16.17836037187811, "SI_output_scale_lr_mult": 2.4740060905127015, "SI_layer_norm": "instance", "SI_gen_final_activ": null, "batch_base2_exponent": 5, "gen_lr": 0.002252812073496261, "gen_b1": 0.3780182972970298, "gen_b2": 0.32535018061489646, "sup_base_criterion": "MSELoss", "IS_disc_hidden_dim": 1, "IS_disc_patchGAN": 1, "IS_disc_lr": 1, "IS_disc_b1": 1, "IS_disc_b2": 1, "IS_disc_adv_criterion": 1, "network_type": "ACT", "train_SI": true, "gen_image_size": 180, "gen_sino_size": 288, "gen_image_channels": 1, "gen_sino_channels": 3}, "time_since_restore": 178.30312943458557, "iterations_since_restore": 42}
{"MSE": 69.62991743534803, "SSIM": 0.7864565078925807, "example_num": 44032, "batch_step": 1376, "epoch": 2, "timestamp": 1773553080, "checkpoint_dir_name": null, "done": false, "training_iteration": 43, "trial_id": "76e49193", "date": "2026-03-15_00-38-00", "time_this_iter_s": 3.7922887802124023, "time_total_s": 182.09541821479797, "pid": 11544, "hostname": "DESKTOP-6E08LRQ", "node_ip": "127.0.0.1", "config": {"SI_gen_mult": 1.1608267138663855, "SI_gen_fill": 0, "SI_gen_neck": "wide", "SI_gen_z_dim": 1368, "SI_pad_mode": "zeros", "SI_dropout": false, "SI_exp_kernel": 4, "SI_gen_hidden_dim": 20, "SI_skip_mode": "conv", "SI_stats_criterion": -1, "SI_moment_1_fraction": -1, "SI_alpha_min": -1, "SI_half_life_examples": -1, "SI_disc_hidden_dim": 1, "SI_disc_patchGAN": 1, "SI_disc_lr": 1, "SI_disc_b1": 1, "SI_disc_b2": 1, "SI_disc_adv_criterion": 1, "SI_normalize": false, "SI_fixedScale": 1, "SI_learnedScale_init": 16.17836037187811, "SI_output_scale_lr_mult": 2.4740060905127015, "SI_layer_norm": "instance", "SI_gen_final_activ": null, "batch_base2_exponent": 5, "gen_lr": 0.002252812073496261, "gen_b1": 0.3780182972970298, "gen_b2": 0.32535018061489646, "sup_base_criterion": "MSELoss", "IS_disc_hidden_dim": 1, "IS_disc_patchGAN": 1, "IS_disc_lr": 1, "IS_disc_b1": 1, "IS_disc_b2": 1, "IS_disc_adv_criterion": 1, "network_type": "ACT", "train_SI": true, "gen_image_size": 180, "gen_sino_size": 288, "gen_image_channels": 1, "gen_sino_channels": 3}, "time_since_restore": 182.09541821479797, "iterations_since_restore": 43}
{"MSE": 82.80575925856829, "SSIM": 0.7941407531034201, "example_num": 45056, "batch_step": 1408, "epoch": 2, "timestamp": 1773553084, "checkpoint_dir_name": null, "done": false, "training_iteration": 44, "trial_id": "76e49193", "date": "2026-03-15_00-38-04", "time_this_iter_s": 4.024267911911011, "time_total_s": 186.11968612670898, "pid": 11544, "hostname": "DESKTOP-6E08LRQ", "node_ip": "127.0.0.1", "config": {"SI_gen_mult": 1.1608267138663855, "SI_gen_fill": 0, "SI_gen_neck": "wide", "SI_gen_z_dim": 1368, "SI_pad_mode": "zeros", "SI_dropout": false, "SI_exp_kernel": 4, "SI_gen_hidden_dim": 20, "SI_skip_mode": "conv", "SI_stats_criterion": -1, "SI_moment_1_fraction": -1, "SI_alpha_min": -1, "SI_half_life_examples": -1, "SI_disc_hidden_dim": 1, "SI_disc_patchGAN": 1, "SI_disc_lr": 1, "SI_disc_b1": 1, "SI_disc_b2": 1, "SI_disc_adv_criterion": 1, "SI_normalize": false, "SI_fixedScale": 1, "SI_learnedScale_init": 16.17836037187811, "SI_output_scale_lr_mult": 2.4740060905127015, "SI_layer_norm": "instance", "SI_gen_final_activ": null, "batch_base2_exponent": 5, "gen_lr": 0.002252812073496261, "gen_b1": 0.3780182972970298, "gen_b2": 0.32535018061489646, "sup_base_criterion": "MSELoss", "IS_disc_hidden_dim": 1, "IS_disc_patchGAN": 1, "IS_disc_lr": 1, "IS_disc_b1": 1, "IS_disc_b2": 1, "IS_disc_adv_criterion": 1, "network_type": "ACT", "train_SI": true, "gen_image_size": 180, "gen_sino_size": 288, "gen_image_channels": 1, "gen_sino_channels": 3}, "time_since_restore": 186.11968612670898, "iterations_since_restore": 44}
{"MSE": 70.15880854427814, "SSIM": 0.8024089396931231, "example_num": 46080, "batch_step": 1440, "epoch": 2, "timestamp": 1773553087, "checkpoint_dir_name": null, "done": false, "training_iteration": 45, "trial_id": "76e49193", "date": "2026-03-15_00-38-07", "time_this_iter_s": 3.717738151550293, "time_total_s": 189.83742427825928, "pid": 11544, "hostname": "DESKTOP-6E08LRQ", "node_ip": "127.0.0.1", "config": {"SI_gen_mult": 1.1608267138663855, "SI_gen_fill": 0, "SI_gen_neck": "wide", "SI_gen_z_dim": 1368, "SI_pad_mode": "zeros", "SI_dropout": false, "SI_exp_kernel": 4, "SI_gen_hidden_dim": 20, "SI_skip_mode": "conv", "SI_stats_criterion": -1, "SI_moment_1_fraction": -1, "SI_alpha_min": -1, "SI_half_life_examples": -1, "SI_disc_hidden_dim": 1, "SI_disc_patchGAN": 1, "SI_disc_lr": 1, "SI_disc_b1": 1, "SI_disc_b2": 1, "SI_disc_adv_criterion": 1, "SI_normalize": false, "SI_fixedScale": 1, "SI_learnedScale_init": 16.17836037187811, "SI_output_scale_lr_mult": 2.4740060905127015, "SI_layer_norm": "instance", "SI_gen_final_activ": null, "batch_base2_exponent": 5, "gen_lr": 0.002252812073496261, "gen_b1": 0.3780182972970298, "gen_b2": 0.32535018061489646, "sup_base_criterion": "MSELoss", "IS_disc_hidden_dim": 1, "IS_disc_patchGAN": 1, "IS_disc_lr": 1, "IS_disc_b1": 1, "IS_disc_b2": 1, "IS_disc_adv_criterion": 1, "network_type": "ACT", "train_SI": true, "gen_image_size": 180, "gen_sino_size": 288, "gen_image_channels": 1, "gen_sino_channels": 3}, "time_since_restore": 189.83742427825928, "iterations_since_restore": 45}
{"MSE": 55.58961170911789, "SSIM": 0.8135334190446883, "example_num": 47104, "batch_step": 1472, "epoch": 2, "timestamp": 1773553091, "checkpoint_dir_name": null, "done": false, "training_iteration": 46, "trial_id": "76e49193", "date": "2026-03-15_00-38-11", "time_this_iter_s": 3.6333742141723633, "time_total_s": 193.47079849243164, "pid": 11544, "hostname": "DESKTOP-6E08LRQ", "node_ip": "127.0.0.1", "config": {"SI_gen_mult": 1.1608267138663855, "SI_gen_fill": 0, "SI_gen_neck": "wide", "SI_gen_z_dim": 1368, "SI_pad_mode": "zeros", "SI_dropout": false, "SI_exp_kernel": 4, "SI_gen_hidden_dim": 20, "SI_skip_mode": "conv", "SI_stats_criterion": -1, "SI_moment_1_fraction": -1, "SI_alpha_min": -1, "SI_half_life_examples": -1, "SI_disc_hidden_dim": 1, "SI_disc_patchGAN": 1, "SI_disc_lr": 1, "SI_disc_b1": 1, "SI_disc_b2": 1, "SI_disc_adv_criterion": 1, "SI_normalize": false, "SI_fixedScale": 1, "SI_learnedScale_init": 16.17836037187811, "SI_output_scale_lr_mult": 2.4740060905127015, "SI_layer_norm": "instance", "SI_gen_final_activ": null, "batch_base2_exponent": 5, "gen_lr": 0.002252812073496261, "gen_b1": 0.3780182972970298, "gen_b2": 0.32535018061489646, "sup_base_criterion": "MSELoss", "IS_disc_hidden_dim": 1, "IS_disc_patchGAN": 1, "IS_disc_lr": 1, "IS_disc_b1": 1, "IS_disc_b2": 1, "IS_disc_adv_criterion": 1, "network_type": "ACT", "train_SI": true, "gen_image_size": 180, "gen_sino_size": 288, "gen_image_channels": 1, "gen_sino_channels": 3}, "time_since_restore": 193.47079849243164, "iterations_since_restore": 46}
{"MSE": 67.43642843514681, "SSIM": 0.7933192015625536, "example_num": 48128, "batch_step": 1504, "epoch": 2, "timestamp": 1773553095, "checkpoint_dir_name": null, "done": false, "training_iteration": 47, "trial_id": "76e49193", "date": "2026-03-15_00-38-15", "time_this_iter_s": 4.299365758895874, "time_total_s": 197.77016425132751, "pid": 11544, "hostname": "DESKTOP-6E08LRQ", "node_ip": "127.0.0.1", "config": {"SI_gen_mult": 1.1608267138663855, "SI_gen_fill": 0, "SI_gen_neck": "wide", "SI_gen_z_dim": 1368, "SI_pad_mode": "zeros", "SI_dropout": false, "SI_exp_kernel": 4, "SI_gen_hidden_dim": 20, "SI_skip_mode": "conv", "SI_stats_criterion": -1, "SI_moment_1_fraction": -1, "SI_alpha_min": -1, "SI_half_life_examples": -1, "SI_disc_hidden_dim": 1, "SI_disc_patchGAN": 1, "SI_disc_lr": 1, "SI_disc_b1": 1, "SI_disc_b2": 1, "SI_disc_adv_criterion": 1, "SI_normalize": false, "SI_fixedScale": 1, "SI_learnedScale_init": 16.17836037187811, "SI_output_scale_lr_mult": 2.4740060905127015, "SI_layer_norm": "instance", "SI_gen_final_activ": null, "batch_base2_exponent": 5, "gen_lr": 0.002252812073496261, "gen_b1": 0.3780182972970298, "gen_b2": 0.32535018061489646, "sup_base_criterion": "MSELoss", "IS_disc_hidden_dim": 1, "IS_disc_patchGAN": 1, "IS_disc_lr": 1, "IS_disc_b1": 1, "IS_disc_b2": 1, "IS_disc_adv_criterion": 1, "network_type": "ACT", "train_SI": true, "gen_image_size": 180, "gen_sino_size": 288, "gen_image_channels": 1, "gen_sino_channels": 3}, "time_since_restore": 197.77016425132751, "iterations_since_restore": 47}
{"MSE": 59.05541080981493, "SSIM": 0.8197460952214897, "example_num": 49152, "batch_step": 1536, "epoch": 2, "timestamp": 1773553099, "checkpoint_dir_name": null, "done": true, "training_iteration": 48, "trial_id": "76e49193", "date": "2026-03-15_00-38-19", "time_this_iter_s": 3.997945547103882, "time_total_s": 201.7681097984314, "pid": 11544, "hostname": "DESKTOP-6E08LRQ", "node_ip": "127.0.0.1", "config": {"SI_gen_mult": 1.1608267138663855, "SI_gen_fill": 0, "SI_gen_neck": "wide", "SI_gen_z_dim": 1368, "SI_pad_mode": "zeros", "SI_dropout": false, "SI_exp_kernel": 4, "SI_gen_hidden_dim": 20, "SI_skip_mode": "conv", "SI_stats_criterion": -1, "SI_moment_1_fraction": -1, "SI_alpha_min": -1, "SI_half_life_examples": -1, "SI_disc_hidden_dim": 1, "SI_disc_patchGAN": 1, "SI_disc_lr": 1, "SI_disc_b1": 1, "SI_disc_b2": 1, "SI_disc_adv_criterion": 1, "SI_normalize": false, "SI_fixedScale": 1, "SI_learnedScale_init": 16.17836037187811, "SI_output_scale_lr_mult": 2.4740060905127015, "SI_layer_norm": "instance", "SI_gen_final_activ": null, "batch_base2_exponent": 5, "gen_lr": 0.002252812073496261, "gen_b1": 0.3780182972970298, "gen_b2": 0.32535018061489646, "sup_base_criterion": "MSELoss", "IS_disc_hidden_dim": 1, "IS_disc_patchGAN": 1, "IS_disc_lr": 1, "IS_disc_b1": 1, "IS_disc_b2": 1, "IS_disc_adv_criterion": 1, "network_type": "ACT", "train_SI": true, "gen_image_size": 180, "gen_sino_size": 288, "gen_image_channels": 1, "gen_sino_channels": 3}, "time_since_restore": 201.7681097984314, "iterations_since_restore": 48}
