{"MSE": 213.1021004319191, "SSIM": 0.10317466956621502, "example_num": 1024, "batch_step": 32, "epoch": 0, "timestamp": 1774174873, "checkpoint_dir_name": null, "done": false, "training_iteration": 1, "trial_id": "9861be1b", "date": "2026-03-22_05-21-13", "time_this_iter_s": 11.316905498504639, "time_total_s": 11.316905498504639, "pid": 5596, "hostname": "DESKTOP-6E08LRQ", "node_ip": "127.0.0.1", "config": {"SI_gen_mult": 1.5821455942234017, "SI_gen_fill": 1, "SI_gen_neck": "narrow", "SI_gen_z_dim": 1793, "SI_pad_mode": "zeros", "SI_dropout": false, "SI_exp_kernel": 4, "SI_gen_hidden_dim": 29, "SI_skip_mode": "none", "SI_stats_criterion": -1, "SI_moment_1_fraction": -1, "SI_alpha_min": -1, "SI_half_life_examples": -1, "SI_disc_hidden_dim": 1, "SI_disc_patchGAN": 1, "SI_disc_lr": 1, "SI_disc_b1": 1, "SI_disc_b2": 1, "SI_disc_adv_criterion": 1, "SI_normalize": false, "SI_fixedScale": 1, "SI_learnedScale_init": 18.421573932979772, "SI_output_scale_lr_mult": 5.354794249313656, "SI_layer_norm": "instance", "SI_gen_final_activ": "Sigmoid", "batch_base2_exponent": 5, "gen_lr": 0.0005027479265277138, "gen_b1": 0.394391028441701, "gen_b2": 0.36840661439119454, "sup_base_criterion": "MSELoss", "IS_disc_hidden_dim": 1, "IS_disc_patchGAN": 1, "IS_disc_lr": 1, "IS_disc_b1": 1, "IS_disc_b2": 1, "IS_disc_adv_criterion": 1, "network_type": "ACT", "train_SI": true, "gen_image_size": 180, "gen_sino_size": 320, "gen_image_channels": 1, "gen_sino_channels": 3, "recon_variant": 1, "frozen_variant": "RECON_SINO"}, "time_since_restore": 11.316905498504639, "iterations_since_restore": 1}
{"MSE": 162.77959769964218, "SSIM": 0.2119963280238153, "example_num": 2048, "batch_step": 64, "epoch": 0, "timestamp": 1774174885, "checkpoint_dir_name": null, "done": false, "training_iteration": 2, "trial_id": "9861be1b", "date": "2026-03-22_05-21-25", "time_this_iter_s": 12.131812810897827, "time_total_s": 23.448718309402466, "pid": 5596, "hostname": "DESKTOP-6E08LRQ", "node_ip": "127.0.0.1", "config": {"SI_gen_mult": 1.5821455942234017, "SI_gen_fill": 1, "SI_gen_neck": "narrow", "SI_gen_z_dim": 1793, "SI_pad_mode": "zeros", "SI_dropout": false, "SI_exp_kernel": 4, "SI_gen_hidden_dim": 29, "SI_skip_mode": "none", "SI_stats_criterion": -1, "SI_moment_1_fraction": -1, "SI_alpha_min": -1, "SI_half_life_examples": -1, "SI_disc_hidden_dim": 1, "SI_disc_patchGAN": 1, "SI_disc_lr": 1, "SI_disc_b1": 1, "SI_disc_b2": 1, "SI_disc_adv_criterion": 1, "SI_normalize": false, "SI_fixedScale": 1, "SI_learnedScale_init": 18.421573932979772, "SI_output_scale_lr_mult": 5.354794249313656, "SI_layer_norm": "instance", "SI_gen_final_activ": "Sigmoid", "batch_base2_exponent": 5, "gen_lr": 0.0005027479265277138, "gen_b1": 0.394391028441701, "gen_b2": 0.36840661439119454, "sup_base_criterion": "MSELoss", "IS_disc_hidden_dim": 1, "IS_disc_patchGAN": 1, "IS_disc_lr": 1, "IS_disc_b1": 1, "IS_disc_b2": 1, "IS_disc_adv_criterion": 1, "network_type": "ACT", "train_SI": true, "gen_image_size": 180, "gen_sino_size": 320, "gen_image_channels": 1, "gen_sino_channels": 3, "recon_variant": 1, "frozen_variant": "RECON_SINO"}, "time_since_restore": 23.448718309402466, "iterations_since_restore": 2}
{"MSE": 178.49700397253036, "SSIM": 0.26985859518754296, "example_num": 3072, "batch_step": 96, "epoch": 0, "timestamp": 1774174898, "checkpoint_dir_name": null, "done": false, "training_iteration": 3, "trial_id": "9861be1b", "date": "2026-03-22_05-21-38", "time_this_iter_s": 12.39389181137085, "time_total_s": 35.842610120773315, "pid": 5596, "hostname": "DESKTOP-6E08LRQ", "node_ip": "127.0.0.1", "config": {"SI_gen_mult": 1.5821455942234017, "SI_gen_fill": 1, "SI_gen_neck": "narrow", "SI_gen_z_dim": 1793, "SI_pad_mode": "zeros", "SI_dropout": false, "SI_exp_kernel": 4, "SI_gen_hidden_dim": 29, "SI_skip_mode": "none", "SI_stats_criterion": -1, "SI_moment_1_fraction": -1, "SI_alpha_min": -1, "SI_half_life_examples": -1, "SI_disc_hidden_dim": 1, "SI_disc_patchGAN": 1, "SI_disc_lr": 1, "SI_disc_b1": 1, "SI_disc_b2": 1, "SI_disc_adv_criterion": 1, "SI_normalize": false, "SI_fixedScale": 1, "SI_learnedScale_init": 18.421573932979772, "SI_output_scale_lr_mult": 5.354794249313656, "SI_layer_norm": "instance", "SI_gen_final_activ": "Sigmoid", "batch_base2_exponent": 5, "gen_lr": 0.0005027479265277138, "gen_b1": 0.394391028441701, "gen_b2": 0.36840661439119454, "sup_base_criterion": "MSELoss", "IS_disc_hidden_dim": 1, "IS_disc_patchGAN": 1, "IS_disc_lr": 1, "IS_disc_b1": 1, "IS_disc_b2": 1, "IS_disc_adv_criterion": 1, "network_type": "ACT", "train_SI": true, "gen_image_size": 180, "gen_sino_size": 320, "gen_image_channels": 1, "gen_sino_channels": 3, "recon_variant": 1, "frozen_variant": "RECON_SINO"}, "time_since_restore": 35.842610120773315, "iterations_since_restore": 3}
{"MSE": 154.64400178194046, "SSIM": 0.32216973265167326, "example_num": 4096, "batch_step": 128, "epoch": 0, "timestamp": 1774174912, "checkpoint_dir_name": null, "done": true, "training_iteration": 4, "trial_id": "9861be1b", "date": "2026-03-22_05-21-52", "time_this_iter_s": 14.73839282989502, "time_total_s": 50.581002950668335, "pid": 5596, "hostname": "DESKTOP-6E08LRQ", "node_ip": "127.0.0.1", "config": {"SI_gen_mult": 1.5821455942234017, "SI_gen_fill": 1, "SI_gen_neck": "narrow", "SI_gen_z_dim": 1793, "SI_pad_mode": "zeros", "SI_dropout": false, "SI_exp_kernel": 4, "SI_gen_hidden_dim": 29, "SI_skip_mode": "none", "SI_stats_criterion": -1, "SI_moment_1_fraction": -1, "SI_alpha_min": -1, "SI_half_life_examples": -1, "SI_disc_hidden_dim": 1, "SI_disc_patchGAN": 1, "SI_disc_lr": 1, "SI_disc_b1": 1, "SI_disc_b2": 1, "SI_disc_adv_criterion": 1, "SI_normalize": false, "SI_fixedScale": 1, "SI_learnedScale_init": 18.421573932979772, "SI_output_scale_lr_mult": 5.354794249313656, "SI_layer_norm": "instance", "SI_gen_final_activ": "Sigmoid", "batch_base2_exponent": 5, "gen_lr": 0.0005027479265277138, "gen_b1": 0.394391028441701, "gen_b2": 0.36840661439119454, "sup_base_criterion": "MSELoss", "IS_disc_hidden_dim": 1, "IS_disc_patchGAN": 1, "IS_disc_lr": 1, "IS_disc_b1": 1, "IS_disc_b2": 1, "IS_disc_adv_criterion": 1, "network_type": "ACT", "train_SI": true, "gen_image_size": 180, "gen_sino_size": 320, "gen_image_channels": 1, "gen_sino_channels": 3, "recon_variant": 1, "frozen_variant": "RECON_SINO"}, "time_since_restore": 50.581002950668335, "iterations_since_restore": 4}
