{"MSE": 220.62577018141747, "SSIM": 0.01481916631470881, "example_num": 1024, "batch_step": 32, "epoch": 0, "timestamp": 1780611924, "checkpoint_dir_name": null, "done": false, "training_iteration": 1, "trial_id": "6aa7ed8f", "date": "2026-06-04_17-25-24", "time_this_iter_s": 5.620713233947754, "time_total_s": 5.620713233947754, "pid": 3044, "hostname": "DESKTOP-6E08LRQ", "node_ip": "127.0.0.1", "config": {"SI_gen_mult": 1.7992970212609598, "SI_gen_fill": 0, "SI_gen_neck": "wide", "SI_gen_z_dim": 995, "SI_pad_mode": "zeros", "SI_dropout": "false", "SI_exp_kernel": 4, "SI_gen_hidden_dim": 23, "SI_skip_mode": "none", "SI_stats_criterion": -1, "SI_moment_1_fraction": -1, "SI_alpha_min": -1, "SI_half_life_examples": -1, "SI_disc_hidden_dim": 1, "SI_disc_patchGAN": 1, "SI_disc_lr": 1, "SI_disc_b1": 1, "SI_disc_b2": 1, "SI_disc_adv_criterion": 1, "SI_normalize": "false", "SI_fixedScale": 1, "SI_learnedScale_init": 1.7314052400496276, "SI_output_scale_lr_mult": 6.393266265152541, "SI_layer_norm": "instance", "SI_gen_final_activ": "ELU", "batch_base2_exponent": 5, "gen_lr": 0.0007609858220515622, "gen_b1": 0.13974492367627356, "gen_b2": 0.12993103279600154, "sup_base_criterion": "VarWeightedMSE", "IS_disc_hidden_dim": 1, "IS_disc_patchGAN": 1, "IS_disc_lr": 1, "IS_disc_b1": 1, "IS_disc_b2": 1, "IS_disc_adv_criterion": 1, "network_type": "ACT", "train_SI": true, "gen_image_size": 180, "gen_sino_size": 320, "gen_image_channels": 1, "gen_sino_channels_SI": 3, "gen_sino_channels_IS": 1, "recon_variant": 2, "frozen_variant": "RECON_SINO"}, "time_since_restore": 5.620713233947754, "iterations_since_restore": 1}
{"MSE": 254.80612760782242, "SSIM": 0.012446523600686987, "example_num": 2048, "batch_step": 64, "epoch": 0, "timestamp": 1780611929, "checkpoint_dir_name": null, "done": false, "training_iteration": 2, "trial_id": "6aa7ed8f", "date": "2026-06-04_17-25-29", "time_this_iter_s": 5.338268995285034, "time_total_s": 10.958982229232788, "pid": 3044, "hostname": "DESKTOP-6E08LRQ", "node_ip": "127.0.0.1", "config": {"SI_gen_mult": 1.7992970212609598, "SI_gen_fill": 0, "SI_gen_neck": "wide", "SI_gen_z_dim": 995, "SI_pad_mode": "zeros", "SI_dropout": "false", "SI_exp_kernel": 4, "SI_gen_hidden_dim": 23, "SI_skip_mode": "none", "SI_stats_criterion": -1, "SI_moment_1_fraction": -1, "SI_alpha_min": -1, "SI_half_life_examples": -1, "SI_disc_hidden_dim": 1, "SI_disc_patchGAN": 1, "SI_disc_lr": 1, "SI_disc_b1": 1, "SI_disc_b2": 1, "SI_disc_adv_criterion": 1, "SI_normalize": "false", "SI_fixedScale": 1, "SI_learnedScale_init": 1.7314052400496276, "SI_output_scale_lr_mult": 6.393266265152541, "SI_layer_norm": "instance", "SI_gen_final_activ": "ELU", "batch_base2_exponent": 5, "gen_lr": 0.0007609858220515622, "gen_b1": 0.13974492367627356, "gen_b2": 0.12993103279600154, "sup_base_criterion": "VarWeightedMSE", "IS_disc_hidden_dim": 1, "IS_disc_patchGAN": 1, "IS_disc_lr": 1, "IS_disc_b1": 1, "IS_disc_b2": 1, "IS_disc_adv_criterion": 1, "network_type": "ACT", "train_SI": true, "gen_image_size": 180, "gen_sino_size": 320, "gen_image_channels": 1, "gen_sino_channels_SI": 3, "gen_sino_channels_IS": 1, "recon_variant": 2, "frozen_variant": "RECON_SINO"}, "time_since_restore": 10.958982229232788, "iterations_since_restore": 2}
{"MSE": 199.73628101265058, "SSIM": 0.03608300229873862, "example_num": 3072, "batch_step": 96, "epoch": 0, "timestamp": 1780611940, "checkpoint_dir_name": null, "done": false, "training_iteration": 3, "trial_id": "6aa7ed8f", "date": "2026-06-04_17-25-40", "time_this_iter_s": 10.32963252067566, "time_total_s": 21.288614749908447, "pid": 3044, "hostname": "DESKTOP-6E08LRQ", "node_ip": "127.0.0.1", "config": {"SI_gen_mult": 1.7992970212609598, "SI_gen_fill": 0, "SI_gen_neck": "wide", "SI_gen_z_dim": 995, "SI_pad_mode": "zeros", "SI_dropout": "false", "SI_exp_kernel": 4, "SI_gen_hidden_dim": 23, "SI_skip_mode": "none", "SI_stats_criterion": -1, "SI_moment_1_fraction": -1, "SI_alpha_min": -1, "SI_half_life_examples": -1, "SI_disc_hidden_dim": 1, "SI_disc_patchGAN": 1, "SI_disc_lr": 1, "SI_disc_b1": 1, "SI_disc_b2": 1, "SI_disc_adv_criterion": 1, "SI_normalize": "false", "SI_fixedScale": 1, "SI_learnedScale_init": 1.7314052400496276, "SI_output_scale_lr_mult": 6.393266265152541, "SI_layer_norm": "instance", "SI_gen_final_activ": "ELU", "batch_base2_exponent": 5, "gen_lr": 0.0007609858220515622, "gen_b1": 0.13974492367627356, "gen_b2": 0.12993103279600154, "sup_base_criterion": "VarWeightedMSE", "IS_disc_hidden_dim": 1, "IS_disc_patchGAN": 1, "IS_disc_lr": 1, "IS_disc_b1": 1, "IS_disc_b2": 1, "IS_disc_adv_criterion": 1, "network_type": "ACT", "train_SI": true, "gen_image_size": 180, "gen_sino_size": 320, "gen_image_channels": 1, "gen_sino_channels_SI": 3, "gen_sino_channels_IS": 1, "recon_variant": 2, "frozen_variant": "RECON_SINO"}, "time_since_restore": 21.288614749908447, "iterations_since_restore": 3}
{"MSE": 184.2717613875866, "SSIM": 0.01666564119327063, "example_num": 4096, "batch_step": 128, "epoch": 0, "timestamp": 1780611956, "checkpoint_dir_name": null, "done": true, "training_iteration": 4, "trial_id": "6aa7ed8f", "date": "2026-06-04_17-25-56", "time_this_iter_s": 15.975891828536987, "time_total_s": 37.264506578445435, "pid": 3044, "hostname": "DESKTOP-6E08LRQ", "node_ip": "127.0.0.1", "config": {"SI_gen_mult": 1.7992970212609598, "SI_gen_fill": 0, "SI_gen_neck": "wide", "SI_gen_z_dim": 995, "SI_pad_mode": "zeros", "SI_dropout": "false", "SI_exp_kernel": 4, "SI_gen_hidden_dim": 23, "SI_skip_mode": "none", "SI_stats_criterion": -1, "SI_moment_1_fraction": -1, "SI_alpha_min": -1, "SI_half_life_examples": -1, "SI_disc_hidden_dim": 1, "SI_disc_patchGAN": 1, "SI_disc_lr": 1, "SI_disc_b1": 1, "SI_disc_b2": 1, "SI_disc_adv_criterion": 1, "SI_normalize": "false", "SI_fixedScale": 1, "SI_learnedScale_init": 1.7314052400496276, "SI_output_scale_lr_mult": 6.393266265152541, "SI_layer_norm": "instance", "SI_gen_final_activ": "ELU", "batch_base2_exponent": 5, "gen_lr": 0.0007609858220515622, "gen_b1": 0.13974492367627356, "gen_b2": 0.12993103279600154, "sup_base_criterion": "VarWeightedMSE", "IS_disc_hidden_dim": 1, "IS_disc_patchGAN": 1, "IS_disc_lr": 1, "IS_disc_b1": 1, "IS_disc_b2": 1, "IS_disc_adv_criterion": 1, "network_type": "ACT", "train_SI": true, "gen_image_size": 180, "gen_sino_size": 320, "gen_image_channels": 1, "gen_sino_channels_SI": 3, "gen_sino_channels_IS": 1, "recon_variant": 2, "frozen_variant": "RECON_SINO"}, "time_since_restore": 37.264506578445435, "iterations_since_restore": 4}
